Workbook

Sheet Revenue Build
B3: Samsara
B4: NASDAQ: IOT | F4: Horizontal | L4: Projected
C5: Date | D5: FY20 | E5: FY21 | F5: FY22 | G5: FY23 | H5: FY24 | I5: FY25 | J5: FY26 | K5: FY27 | L5: FY28 | M5: FY29 | N5: FY30
B7: Revenue Build By Customer Segment
B9: BoP > $100K ARR customers, # of customers | D9: 64 | E9: =D11 -> 255 | F9: =E11 -> 452 | G9: =F11 -> 806 | H9: =G11 -> 1237 | I9: =H11 -> 1848 | J9: =I11 -> 2484 | K9: =J11 -> 3200 | L9: =K11 -> 3959 | ... N9: =M11 -> 5583
B10: > $100K ARR customers net additions, # of customers | D10: 191 | E10: 197 | F10: 354 | G10: 431 | H10: 611 | I10: 636 | J10: 716 | K10: 759 | L10: 824 | M10: 800 | N10: 750
B11: EoP > $100K ARR customers, # of customers | D11: =D9+D10 -> 255 | E11: =E9+E10 -> 452 | F11: =F9+F10 -> 806 | G11: =G9+G10 -> 1237 | H11: =H9+H10 -> 1848 | I11: =I9+I10 -> 2484 | J11: =J9+J10 -> 3200 | K11: =K9+K10 -> 3959 | ... N11: =N9+N10 -> 6333
B12: Y/Y EoP > $100K ARR customers growth, % | E12: =E11/D11-1 -> 0.77254902 | F12: =F11/E11-1 -> 0.78318584 | G12: =G11/F11-1 -> 0.53473945 | H12: =H11/G11-1 -> 0.49393694 | I12: =I11/H11-1 -> 0.34415584 | J12: =J11/I11-1 -> 0.28824477 | K12: =K11/J11-1 -> 0.2371875 | L12: =L11/K11-1 -> 0.20813337 | ... N12: =N11/M11-1 -> 0.13433638
B14: BoP $5K - $100K ARR customers, # of customers | G14: 13694 | H14: =G16 -> 18063 | I14: 14652 | J14: =I16 -> 17516 | K14: =J16 -> 20229 | L14: =K16 -> 22629 | M14: =L16 -> 24929 | N14: =M16 -> 27129
B15: $10K - $100K ARR customers net additions, # of customers | G15: 4369 | H15: 4489 | I15: 2864 | J15: 2713 | K15: 2400 | L15: 2300 | M15: 2200 | N15: 2100
B16: EoP $5K - $100K ARR customers, # of customers | G16: =G14+G15 -> 18063 | H16: =H14+H15 -> 22552 | I16: =I14+I15 -> 17516 | J16: =J14+J15 -> 20229 | K16: =K14+K15 -> 22629 | L16: =L14+L15 -> 24929 | M16: =M14+M15 -> 27129 | N16: =N14+N15 -> 29229
B17: Y/Y EoP $5K - $100K ARR customers growth, % | H17: =H16/G16-1 -> 0.24851907 | I17: =I16/H16-1 -> -0.22330614 | J17: =J16/I16-1 -> 0.15488696 | K17: =K16/J16-1 -> 0.11864155 | L17: =L16/K16-1 -> 0.10163949 | M17: =M16/L16-1 -> 0.088250632 | N17: =N16/M16-1 -> 0.07740794
B19: BoP Core Customers, # of customers | G19: 14500 | H19: =G21 -> 19300 | I19: 16500 | J19: =I21 -> 20000 | K19: =J21 -> 23200 | L19: =K21 -> 26220 | M19: =L21 -> 29170 | N19: =M21 -> 31570
B20: Core customers net additions, # of customers | G20: 4800 | H20: 5100 | I20: 3500 | J20: 3200 | K20: 3020 | L20: 2950 | M20: 2400 | N20: 2400
B21: EoP Core Customers, # of customers | G21: =G19+G20 -> 19300 | H21: =H19+H20 -> 24400 | I21: 20000 | J21: =J19+J20 -> 23200 | K21: =K19+K20 -> 26220 | L21: =L19+L20 -> 29170 | M21: =M19+M20 -> 31570 | N21: =N19+N20 -> 33970
B22: Y/Y Core customers growth, % | H22: =H21/G21-1 -> 0.2642487 | I22: =I21/H21-1 -> -0.18032787
B24: ARR per > $100k ARR customers, ARR/customer | G24: 308509 | H24: 310081 | I24: 340404 | J24: =I24*(1+J25) -> 374444.4 | K24: =J24*(1+K25) -> 408144.4 | L24: =K24*(1+L25) -> 440795.95 | M24: =L24*(1+M25) -> 471651.66 | N24: =M24*(1+N25) -> 495234.25
B25: Y/Y ARR per > $100k ARR customer growth, % | H25: =H24/G24-1 -> 0.0050954753 | I25: =I24/H24-1 -> 0.097790577 | J25: 0.1 | K25: 0.09 | L25: 0.08 | M25: 0.07 | N25: 0.05
B26: ARR per $5K-100K ARR customers, ARR/customer | G26: 20687 | H26: 21500 | I26: 29131 | J26: =I26*(1+J27) -> 30587.55 | K26: =J26*(1+K27) -> 31811.052 | L26: =K26*(1+L27) -> 32447.273 | M26: =L26*(1+M27) -> 33420.691 | N26: =M26*(1+N27) -> 33754.898 | P26: =(J24-I24)*J10 -> 24372926
B27: Y/Y ARR per $5K-$100K ARR customer growth, % | H27: =H26/G26-1 -> 0.039300044 | I27: =I26/H26-1 -> 0.35493023 | J27: 0.05 | K27: 0.04 | L27: 0.02 | M27: 0.03 | N27: 0.01 | P27: =J29-I29 -> 352.62208
P28: =I24*J11 -> 1089292800
B29: > $100k ARR customers ARR, mm | G29: 381.6 | H29: 573 | I29: 845.6 | J29: =J24*J11/1000000 -> 1198.2221 | K29: =K24*K11/1000000 -> 1615.8437 | L29: =L24*L11/1000000 -> 2108.327 | M29: =M24*M11/1000000 -> 2633.2312 | N29: =N24*N11/1000000 -> 3136.3185 | P29: =P28*1.1 -> 1198222080
B30: Y/Y > $100 ARR customers ARR growth, % | H30: =H29/G29-1 -> 0.50157233 | I30: =I29/H29-1 -> 0.47574171 | J30: =J29/I29-1 -> 0.41700814 | K30: =K29/J29-1 -> 0.34853438 | L30: =L29/K29-1 -> 0.30478404 | M30: =M29/L29-1 -> 0.24896718 | N30: =N29/M29-1 -> 0.1910532 | P30: =P29-P28 -> 108929280
B31: $10K - $100K ARR customers ARR, mm | G31: 373.7 | H31: 484.9 | I31: 510.3 | J31: =J26*J16/1000000 -> 618.75555 | K31: =K26*K16/1000000 -> 719.8523 | L31: =L26*L16/1000000 -> 808.87807 | M31: =M26*M16/1000000 -> 906.66993 | N31: =N26*N16/1000000 -> 986.62192 | P31: =P30/(P27*1000000) -> 0.30891225
B32: Y/Y $5K - $100K ARR customers ARR growth, % | H32: =H31/G31-1 -> 0.29756489 | I32: =I31/H31-1 -> 0.052381934 | J32: =J31/I31-1 -> 0.21253292 | K32: =K31/J31-1 -> 0.16338722 | L32: =L31/K31-1 -> 0.12367228 | M32: =M31/L31-1 -> 0.12089815 | N32: =N31/M31-1 -> 0.088182019
B33: < $10K ARR customers ARR, mm | I33: 102.1 | J33: =I33*(1+J34) -> 113.331 | K33: =J33*(1+K34) -> 123.53079 | L33: =K33*(1+L34) -> 130.94264 | M33: =L33*(1+M34) -> 137.48977 | N33: =M33*(1+N34) -> 142.98936
B34: Y/Y < $10K ARR customers ARR growth, % | I34: 0.12 | J34: 0.11 | K34: 0.09 | L34: 0.06 | M34: 0.05 | N34: 0.04
B35: Total ARR, mm | G35: 795.1 | H35: 1102 | I35: 1457.9 | J35: =J29+J31+J33 -> 1930.3086 | K35: =K29+K31+K33 -> 2459.2267 | L35: =L29+L31+L33 -> 3048.1477 | M35: =M29+M31+M33 -> 3677.3909 | N35: =N29+N31+N33 -> 4265.9298
B36: Y/Y Total ARR growth, % | H36: =H35/G35-1 -> 0.38598918 | I36: =I35/H35-1 -> 0.32295826 | J36: =J35/I35-1 -> 0.32403363 | K36: =K35/J35-1 -> 0.27400702 | L36: =L35/K35-1 -> 0.23947404 | M36: =M35/L35-1 -> 0.20643462 | N36: =N35/M35-1 -> 0.1600425
B38: > $100k ARR customers ARR mix, % | G38: 0.48 | H38: 0.52 | I38: 0.58 | J38: =J29/J35 -> 0.62074119 | K38: =K29/K35 -> 0.65705355 | L38: =L29/L35 -> 0.69167482 | M38: =M29/M35 -> 0.71605964 | N38: =N29/N35 -> 0.73520162
B39: $10K - $100K ARR customers ARR mix, % | G39: 0.47 | H39: 0.44 | I39: 0.35 | J39: =J31/J35 -> 0.32054747 | K39: =K31/K35 -> 0.29271489 | L39: =L31/L35 -> 0.26536708 | M39: =M31/M35 -> 0.2465525 | N39: =N31/N35 -> 0.23127946
B40: < $10K ARR customers ARR mix, % | G40: 0.05 | H40: 0.03 | I40: 0.07 | J40: =J33/J35 -> 0.058711337 | K40: =K33/K35 -> 0.050231558 | L40: =L33/L35 -> 0.042958101 | M40: =M33/M35 -> 0.037387858 | N40: =N33/N35 -> 0.03351892
B41: Total ARR mix, % | G41: =G38+G39+G40 -> 1 | H41: 1 | I41: =I38+I39+I40 -> 1 | J41: =J38+J39+J40 -> 1 | K41: =K38+K39+K40 -> 1 | L41: =L38+L39+L40 -> 1 | M41: =M38+M39+M40 -> 1 | N41: =N38+N39+N40 -> 1
B43: Subscription Revenue, mm | G43: 639.5 | H43: 919.4 | I43: 1225.8 | J43: =0.85*(J29+J31) -> 1544.431 | K43: =0.85*(K29+K31) -> 1985.3416 | L43: =0.85*(L29+L31) -> 2479.6243 | M43: =0.85*(M29+M31) -> 3008.916 | N43: =0.85*(N29+N31) -> 3504.4993
B44: Y/Y Subscription revenue growth, % | H44: =H43/G43-1 -> 0.43768569 | I44: =I43/H43-1 -> 0.33326082 | J44: =J43/I43-1 -> 0.25993717 | K44: =K43/J43-1 -> 0.28548416 | L44: =L43/K43-1 -> 0.24896611 | M44: =M43/L43-1 -> 0.2134564 | N44: =N43/M43-1 -> 0.16470495
B45: Other revenue, mm | G45: 13 | H45: 18 | I45: 23.4 | J45: =J33*0.85 -> 96.33135 | K45: =K33*0.85 -> 105.00117 | L45: =L33*0.85 -> 111.30124 | M45: =M33*0.85 -> 116.8663 | N45: =N33*0.85 -> 121.54096
B46: Y/Y Other revenue growth, % | H46: =H45/G45-1 -> 0.38461538 | I46: =I45/H45-1 -> 0.3 | J46: 0.28 | K46: 0.26 | L46: 0.25 | M46: 0.25 | N46: 0.24
B47: Total Revenues, mm | D47: 119.865 | E47: 249.905 | F47: 428.345 | G47: =G43+G45 -> 652.5 | H47: =H43+H45 -> 937.4 | I47: =I43+I45 -> 1249.2 | J47: =J43+J45 -> 1640.7623 | K47: =K43+K45 -> 2090.3427 | L47: =L43+L45 -> 2590.9256 | M47: =M43+M45 -> 3125.7823 | N47: =N43+N45 -> 3626.0403
B48: Y/Y Total revenue growth, % | E48: =E47/D47-1 -> 1.0848872 | F48: =F47/E47-1 -> 0.71403133 | G48: =G47/F47-1 -> 0.52330481 | H48: =H47/G47-1 -> 0.43662835 | I48: =I47/H47-1 -> 0.33262215 | J48: =J47/I47-1 -> 0.31345048 | K48: =K47/J47-1 -> 0.27400702 | L48: =L47/K47-1 -> 0.23947404 | ... N48: =N47/M47-1 -> 0.1600425
B51: Revenue Build
B53: Revenue | D53: =IS!B10 -> 119.865 | E53: =IS!C10 -> 249.905 | F53: =IS!D10 -> 428.345 | G53: =IS!E10 -> 652.545 | H53: =IS!F10 -> 937.385 | I53: =IS!G10 -> 1249.199 | J53: =J56*J57 -> 1635.4986 | K53: =K56*K57 -> 2047.0892 | L53: =L56*L57 -> 2547.115 | M53: =M56*M57 -> 3077.8222 | N53: =N56*N57 -> 3639.7161
B54: % growth | E54: =E53/D53-1 -> 1.0848872 | F54: =F53/E53-1 -> 0.71403133 | G54: =G53/F53-1 -> 0.52340987 | H54: =H53/G53-1 -> 0.43650629 | I54: =I53/H53-1 -> 0.3326424 | J54: =J53/I53-1 -> 0.30923783 | K54: =K53/J53-1 -> 0.25166065 | L54: =L53/K53-1 -> 0.24426185 | ... N54: =N53/M53-1 -> 0.1825622
D56: =D53/D57 -> 0.61786082 | E56: =E53/E57 -> 0.73285924 | F56: =F53/F57 -> 0.76764337 | G56: =G53/G57 -> 0.8207566 | H56: =H53/H57 -> 0.85063626 | I56: =I53/I57 -> 0.85686643 | J56: =AVERAGE(H56:I56) -> 0.85375134 | K56: =J56 -> 0.85375134 | L56: =K56 -> 0.85375134 | M56: =L56 -> 0.85375134 | N56: =M56 -> 0.85375134
B57: ARR | D57: ='Multiple Periods'!G9 -> 194 | E57: ='Multiple Periods'!H9 -> 341 | F57: ='Multiple Periods'!I9 -> 558 | G57: ='Multiple Periods'!J9 -> 795.053 | H57: ='Multiple Periods'!K9 -> 1101.981 | I57: ='Multiple Periods'!L9 -> 1457.869 | J57: =J59+J62+J65 -> 1915.6615 | K57: =K59+K62+K65 -> 2397.7581 | L57: =L59+L62+L65 -> 2983.439 | M57: =M59+M62+M65 -> 3605.0569 | N57: =N59+N62+N65 -> 4263.204
B58: % growth | J58: =J57/I57-1 -> 0.31401484 | K58: =K57/J57-1 -> 0.25166065 | L58: =L57/K57-1 -> 0.24426185 | M58: =M57/L57-1 -> 0.20835617 | N58: =N57/M57-1 -> 0.1825622
B59: Telematics | I59: =I79 -> 600 | J59: =J79 -> 748.05984 | K59: =K79 -> 901.75213 | L59: =L79 -> 1061.2929 | M59: =M79 -> 1226.8546 | N59: =N79 -> 1398.6142
B60: % growth | J60: =J59/I59-1 -> 0.2467664 | K60: =K59/J59-1 -> 0.20545455 | L60: =L59/K59-1 -> 0.17692308 | M60: =M59/L59-1 -> 0.156 | N60: =N59/M59-1 -> 0.14
B61: % ARR | J61: =J59/J57 -> 0.39049688 | K61: =K59/K57 -> 0.37608136 | L61: =L59/L57 -> 0.35572804 | M61: =M59/M57 -> 0.3403149 | N61: =N59/N57 -> 0.32806646
B62: Camera | I62: =I96 -> 700 | J62: =J96 -> 965.52935 | K62: =K96 -> 1241.3949 | L62: =L96 -> 1603.8822 | M62: =M96 -> 1980.3724 | N62: =N96 -> 2371.2807
B63: % growth | J63: =J62/I62-1 -> 0.37932764 | K63: =K62/J62-1 -> 0.28571429 | L63: =L62/K62-1 -> 0.292 | M63: =M62/L62-1 -> 0.23473684 | N63: =N62/M62-1 -> 0.1973913
B64: % ARR | J64: =J62/J57 -> 0.50401877 | K64: =K62/K57 -> 0.51773148 | L64: =L62/L57 -> 0.5375951 | M64: =M62/M57 -> 0.54933181 | N64: =N62/N57 -> 0.55622033
B65: Other | I65: =I57-I59-I62 -> 157.869 | J65: =I65*(1+J66) -> 202.07232 | K65: =J65*(1+K66) -> 254.61112 | L65: =K65*(1+L66) -> 318.2639 | M65: =L65*(1+M66) -> 397.82988 | N65: =M65*(1+N66) -> 493.30905
B66: %growth | I66: 0.3 | J66: 0.28 | K66: 0.26 | L66: 0.25 | M66: 0.25 | N66: 0.24
B67: %ARR | J67: =J65/J57 -> 0.10548436 | K67: =K65/K57 -> 0.10618716 | L67: =L65/L57 -> 0.10667686 | M67: =M65/M57 -> 0.11035329 | N67: =N65/N57 -> 0.11571322
B69: Telematics Build
B71: Total North American Commercial Vehicles | I71: 35 | J71: 35 | K71: 35 | L71: 35 | M71: 35 | N71: 35
B72: North American Commercial Vehicle Penetration | I72: 0.09 | J72: 0.1 | K72: 0.11 | L72: 0.12 | M72: 0.13 | N72: 0.14
B73: Total NA Vehicles Served | I73: 3.15 | J73: =J72*J71 -> 3.5 | K73: =K72*K71 -> 3.85 | L73: =L72*L71 -> 4.2 | M73: =M72*M71 -> 4.55 | N73: =N72*N71 -> 4.9
B75: Total European Commercial Vehicles | I75: 45 | J75: 45 | K75: 45 | L75: 45 | M75: 45 | N75: 45
B76: European Commercial Vehicle Penetration | I76: 0.01 | J76: 0.02 | K76: 0.03 | L76: 0.04 | M76: 0.05 | N76: 0.06
B77: Total European Vehicles Served | I77: 0.45 | J77: =J76*J75 -> 0.9 | K77: =K76*K75 -> 1.35 | L77: =L76*L75 -> 1.8 | M77: =M76*M75 -> 2.25 | N77: =N76*N75 -> 2.7
B79: Total Telematics ARR | I79: 600 | J79: =J82*J81 -> 748.05984 | K79: =K82*K81 -> 901.75213 | L79: =L82*L81 -> 1061.2929 | M79: =M82*M81 -> 1226.8546 | N79: =N82*N81 -> 1398.6142
B80: y/y growth | I80: 0.25 | J80: =J79/I79-1 -> 0.2467664 | K80: =K79/J79-1 -> 0.20545455 | L80: =L79/K79-1 -> 0.17692308 | M80: =M79/L79-1 -> 0.156 | N80: =N79/M79-1 -> 0.14
B81: Total Vehicles Served | I81: 3.6 | J81: =J73+J77 -> 4.4 | K81: =K73+K77 -> 5.2 | L81: =L73+L77 -> 6 | M81: =M73+M77 -> 6.8 | N81: =N73+N77 -> 7.6
B82: Telematics ARPU | I82: 166.67 | J82: =J83*12 -> 170.0136 | K82: =K83*12 -> 173.41387 | L82: =L83*12 -> 176.88215 | M82: =M83*12 -> 180.41979 | N82: =N83*12 -> 184.02819
B83: Implied Monthly Revenue/Vehicle | I83: 13.89 | J83: =I83*(1+J84) -> 14.1678 | K83: =J83*(1+K84) -> 14.451156 | L83: =K83*(1+L84) -> 14.740179 | M83: =L83*(1+M84) -> 15.034983 | N83: =M83*(1+N84) -> 15.335682
B84: y/y growth | J84: 0.02 | K84: 0.02 | L84: 0.02 | M84: 0.02 | N84: 0.02
B86: Camera Build
B88: Total North American Commercial Vehicles | I88: 35 | J88: =I88 -> 35 | K88: =J88 -> 35 | L88: =K88 -> 35 | M88: =L88 -> 35 | N88: =M88 -> 35
B89: North American Commercial Vehicle Penetration | I89: 0.04 | J89: 0.05 | K89: 0.06 | L89: 0.07 | M89: 0.08 | N89: 0.09
B90: Total NA Vehicles Served | I90: 1.4 | J90: =J89*J88 -> 1.75 | K90: =K89*K88 -> 2.1 | L90: =L89*L88 -> 2.45 | M90: =M89*M88 -> 2.8 | N90: =N89*N88 -> 3.15
B92: Total European Commercial Vehicles | I92: 45 | J92: =I92 -> 45 | K92: =J92 -> 45 | L92: =K92 -> 45 | M92: =L92 -> 45 | N92: =M92 -> 45
B93: European Commercial Vehicle Penetration | I93: 0.01 | J93: 0.014 | K93: 0.02 | L93: 0.03 | M93: 0.04 | N93: 0.05
B94: Total European Vehicles Served | I94: 0.36 | J94: =J93*J92 -> 0.63 | K94: =K93*K92 -> 0.9 | L94: =L93*L92 -> 1.35 | M94: =M93*M92 -> 1.8 | N94: =N93*N92 -> 2.25
B96: Total Video-Based Safety ARR | I96: 700 | J96: =J98*J99 -> 965.52935 | K96: =K98*K99 -> 1241.3949 | L96: =L98*L99 -> 1603.8822 | M96: =M98*M99 -> 1980.3724 | N96: =N98*N99 -> 2371.2807
B97: y/y growth | I97: 0.3 | J97: =J96/I96-1 -> 0.37932764 | K97: =K96/J96-1 -> 0.28571429 | L97: =L96/K96-1 -> 0.292 | M97: =M96/L96-1 -> 0.23473684 | N97: =N96/M96-1 -> 0.1973913
B98: Total Vehicles Served | I98: 1.76 | J98: =J90+J94 -> 2.38 | K98: =K90+K94 -> 3 | L98: =L90+L94 -> 3.8 | M98: =M90+M94 -> 4.6 | N98: =N90+N94 -> 5.4
B99: Telematics ARPU | I99: 397.73 | J99: =J100*12 -> 405.6846 | K99: =K100*12 -> 413.79829 | L99: =L100*12 -> 422.07426 | M99: =M100*12 -> 430.51574 | N99: =N100*12 -> 439.12606
B100: Implied Monthly Revenue/Vehicle | I100: =I99/12 -> 33.144167 | J100: =I100*(1+J101) -> 33.80705 | K100: =J100*(1+K101) -> 34.483191 | L100: =K100*(1+L101) -> 35.172855 | M100: =L100*(1+M101) -> 35.876312 | N100: =M100*(1+N101) -> 36.593838
B101: y/y growth | J101: 0.02 | K101: 0.02 | L101: 0.02 | M101: 0.02 | N101: 0.02

Sheet Operating Model
B2: Samsara
B3: NASDAQ: IOT | H3: Historicals | N3: Projected
E4: Date | F4: FY20 | G4: FY21 | H4: FY22 | I4: FY23 | J4: FY24 | K4: FY25 | L4: FY26E | M4: FY27E | N4: FY28E | O4: FY29E | P4: FY30E
B6: Operating Model
B8: Revenue | F8: ='Revenue Build'!D47 -> 119.865 | G8: ='Revenue Build'!E47 -> 249.905 | H8: ='Revenue Build'!F47 -> 428.345 | I8: ='Revenue Build'!G47 -> 652.5 | J8: ='Revenue Build'!H47 -> 937.4 | K8: ='Revenue Build'!I47 -> 1249.2 | L8: ='Revenue Build'!J47 -> 1640.7623 | M8: ='Revenue Build'!K47 -> 2090.3427 | ... P8: ='Revenue Build'!N47 -> 3626.0403
B9: % growth | G9: =G8/F8-1 -> 1.0848872 | H9: =H8/G8-1 -> 0.71403133 | I9: =I8/H8-1 -> 0.52330481 | J9: =J8/I8-1 -> 0.43662835 | K9: =K8/J8-1 -> 0.33262215 | L9: =L8/K8-1 -> 0.31345048 | M9: =M8/L8-1 -> 0.27400702 | N9: =N8/M8-1 -> 0.23947404 | ... P9: =P8/O8-1 -> 0.1600425
B11: COGS | F11: =F8-F13 -> 48.316 | G11: =G8-G13 -> 75.38 | H11: =H8-H13 -> 118.14 | I11: =I8-I13 -> 173.145 | J11: =J8-J13 -> 234.322 | K11: =K8-K13 -> 282.973 | L11: =L8-L13 -> 370.81229 | M11: =M8-M13 -> 470.32712 | ... P11: =P8-P13 -> 779.59866
B13: Gross Profit | F13: ='Multiple Periods'!G114 -> 71.549 | G13: ='Multiple Periods'!H114 -> 174.525 | H13: ='Multiple Periods'!I114 -> 310.205 | I13: ='Multiple Periods'!J114 -> 479.355 | J13: ='Multiple Periods'!K114 -> 703.078 | K13: ='Multiple Periods'!L114 -> 966.227 | L13: =L14*L8 -> 1269.95 | M13: =M14*M8 -> 1620.0156 | N13: =N14*N8 -> 2015.7401 | O13: =O14*O8 -> 2438.1102 | P13: =P14*P8 -> 2846.4416
B14: % Margin | F14: =F13/F8 -> 0.59691319 | G14: =G13/G8 -> 0.69836538 | H14: =H13/H8 -> 0.72419428 | I14: =I13/I8 -> 0.73464368 | J14: =J13/J8 -> 0.75002987 | K14: =K13/K8 -> 0.77347663 | L14: 0.774 | M14: 0.775 | N14: 0.778 | O14: 0.78 | P14: 0.785
B16: Operating Expenses
B17: Research & Development Expense | F17: ='Multiple Periods'!G118 -> 66.812 | G17: ='Multiple Periods'!H118 -> 85.955 | H17: ='Multiple Periods'!I118 -> 102.276 | I17: ='Multiple Periods'!J118 -> 187.405 | J17: ='Multiple Periods'!K118 -> 163.361 | K17: ='Multiple Periods'!L118 -> 192.466 | L17: =L18*L$8 -> 251.03664 | M17: =M18*M$8 -> 315.64175 | N17: =N18*N$8 -> 383.45698 | O17: =O18*O$8 -> 459.49 | P17: =P18*P$8 -> 525.77584
B18: % Revenue | F18: =F17/F8 -> 0.55739373 | G18: =G17/G8 -> 0.3439507 | H18: =H17/H8 -> 0.23877015 | I18: =I17/I8 -> 0.28721073 | J18: =J17/J8 -> 0.17427032 | K18: =K17/K8 -> 0.15407141 | L18: 0.153 | M18: 0.151 | N18: 0.148 | O18: 0.147 | P18: 0.145
B20: Selling, & Marketing Expense | F20: ='Multiple Periods'!G119 -> 179.393 | G20: ='Multiple Periods'!H119 -> 195.315 | H20: ='Multiple Periods'!I119 -> 228.661 | I20: ='Multiple Periods'!J119 -> 316.026 | J20: ='Multiple Periods'!K119 -> 411.446 | K20: ='Multiple Periods'!L119 -> 511.177 | L20: =L21*L$8 -> 638.25655 | M20: =M21*M$8 -> 804.78195 | N20: =N21*N$8 -> 979.36986 | O20: =O21*O$8 -> 1169.0426 | P20: =P21*P$8 -> 1345.261
B21: % Revenue | F21: =F20/F8 -> 1.4966254 | G21: =G20/G8 -> 0.78155699 | H21: =H20/H8 -> 0.53382437 | I21: =I20/I8 -> 0.48433103 | J21: =J20/J8 -> 0.43892255 | K21: =K20/K8 -> 0.40920349 | L21: 0.389 | M21: 0.385 | N21: 0.378 | O21: 0.374 | P21: 0.371
B23: General & Administrative | F23: ='Multiple Periods'!G120 -> 44.953 | G23: ='Multiple Periods'!H120 -> 70.402 | H23: ='Multiple Periods'!I120 -> 93.346 | I23: ='Multiple Periods'!J120 -> 117.083 | J23: ='Multiple Periods'!K120 -> 127.001 | K23: ='Multiple Periods'!L120 -> 149.032 | L23: =L24*L$8 -> 185.40614 | M23: =M24*M$8 -> 225.75702 | N23: =N24*N$8 -> 264.27441 | O23: =O24*O$8 -> 293.82354 | P23: =P24*P$8 -> 326.34363
B24: % Revenue | F24: =F23/F8 -> 0.37503024 | G24: =G23/G8 -> 0.28171505 | H24: =H23/H8 -> 0.21792247 | I24: =I23/I8 -> 0.17943755 | J24: =J23/J8 -> 0.13548218 | K24: =K23/K8 -> 0.11930195 | L24: 0.113 | M24: 0.108 | N24: 0.102 | O24: 0.094 | P24: 0.09
B26: Operating Income | F26: =F13-SUM(F17,F20,F23) -> -219.609 | G26: =G13-SUM(G17,G20,G23) -> -177.147 | H26: =Sheet2!I21 -> -76.975 | I26: =I13-SUM(I17,I20,I23) -> -141.159 | J26: =J13-SUM(J17,J20,J23) -> 1.27 | K26: =K13-SUM(K17,K20,K23) -> 113.552 | L26: =L13-SUM(L17,L20,L23) -> 195.25072 | M26: =M13-SUM(M17,M20,M23) -> 273.8349 | N26: =N13-SUM(N17,N20,N23) -> 388.63883 | O26: =O13-SUM(O17,O20,O23) -> 515.75408 | P26: =P13-SUM(P17,P20,P23) -> 649.06121
B27: % Revenue | K27: =K26/K8 -> 0.090899776 | L27: =L26/L8 -> 0.119 | M27: =M26/M8 -> 0.131 | N27: =N26/N8 -> 0.15 | O27: =O26/O8 -> 0.165 | P27: =P26/P8 -> 0.179
B29: Non-Operating Income | F29: =Sheet1!C22 -> -2.934 | G29: =Sheet1!D22 -> 0.642 | H29: =Sheet1!E22 -> 0.002 | I29: =Sheet1!F22 -> -15.62 | J29: =Sheet1!G22 -> -39.964 | K29: =Sheet1!H22 -> -39.559 | L29: 0 | M29: 0 | N29: 0 | O29: 0 | P29: 0
B31: Pre-Tax Income | F31: =F26-F29 -> -216.675 | G31: =G26-G29 -> -177.789 | H31: =H26-H29 -> -76.977 | I31: =I26-I29 -> -125.539 | J31: =J26-J29 -> 41.234 | K31: =K26-K29 -> 153.111 | L31: =L26 -> 195.25072 | M31: =M26 -> 273.8349 | N31: =N26 -> 388.63883 | O31: =O26 -> 515.75408 | P31: =P26 -> 649.06121
B33: Income Tax Expense | F33: =Sheet1!C28 -> 0.34 | G33: =Sheet1!D28 -> 0.087 | H33: =Sheet1!E28 -> 1.174 | I33: =Sheet1!F28 -> 3.587 | J33: =Sheet1!G28 -> 3.343 | K33: =Sheet1!H28 -> 4.493 | L33: =L34*L31 -> 9.7625359 | M33: =M34*M31 -> 13.691745 | N33: =N34*N31 -> 19.431942 | O33: =O34*O31 -> 25.787704 | P33: =P34*P31 -> 32.453061
B34: % EBT | J34: =J33/J31 -> 0.081073871 | K34: =K33/K31 -> 0.029344724 | L34: 0.05 | M34: 0.05 | N34: 0.05 | O34: 0.05 | P34: 0.05
B36: Net Income | F36: =F31-F33 -> -217.015 | G36: =G31-G33 -> -177.876 | H36: =H31-H33 -> -78.151 | I36: =I31-I33 -> -129.126 | J36: =J31-J33 -> 37.891 | K36: =K31-K33 -> 148.618 | L36: =L31-L33 -> 185.48818 | M36: =M31-M33 -> 260.14315 | ... P36: =P31-P33 -> 616.60815
B37: % growth | K37: =K36/J36-1 -> 2.9222507 | L37: =L36/K36-1 -> 0.24808692 | M37: =M36/L36-1 -> 0.40247832 | N37: =N36/M36-1 -> 0.41924509 | O37: =O36/N36-1 -> 0.32707808 | P37: =P36/O36-1 -> 0.25847034
B40: Short Term Recievables | F40: =Sheet3!C10 -> 34.213 | G40: =Sheet3!D10 -> 42.248 | H40: =Sheet3!E10 -> 81.987 | I40: =Sheet3!F10 -> 122.867 | J40: =Sheet3!G10 -> 161.829 | K40: =Sheet3!H10 -> 234.016 | L40: =L41*L8/365 -> 298.20232 | M40: =M41*M8/365 -> 379.91184 | N40: =N41*N8/365 -> 470.89087 | O40: =O41*O8/365 -> 568.09905 | P40: =P41*P8/365 -> 659.01904
B41: DSO | F41: =F40/F8*365 -> 104.18175 | G41: =G40/G8*365 -> 61.705528 | H41: =H40/H8*365 -> 69.862506 | I41: =I40/I8*365 -> 68.730199 | J41: =J40/J8*365 -> 63.012145 | K41: =K40/K8*365 -> 68.376433 | L41: =AVERAGE(G41:K41) -> 66.337362 | M41: =L41 -> 66.337362 | N41: =M41 -> 66.337362 | O41: =N41 -> 66.337362 | P41: =O41 -> 66.337362
B43: Inventories | F43: =Sheet3!C14 -> 16.516 | G43: =Sheet3!D14 -> 13.674 | H43: =Sheet3!E14 -> 33.067 | I43: =Sheet3!F14 -> 40.571 | J43: =Sheet3!G14 -> 22.238 | K43: =Sheet3!H14 -> 38.911 | L43: =L44*L11/365 -> 57.689674 | M43: =M44*M11/365 -> 73.171842 | N43: =N44*N11/365 -> 89.485337 | O43: =O44*O11/365 -> 106.98561 | P43: =P44*P11/365 -> 121.28722
B44: DIO | F44: =F43/F11*365 -> 124.76902 | G44: =G43/G11*365 -> 66.211329 | H44: =H43/H11*365 -> 102.16231 | I44: =I43/I11*365 -> 85.526091 | J44: =J43/J11*365 -> 34.639812 | K44: =K43/K11*365 -> 50.190354 | L44: =AVERAGE(I44:K44) -> 56.785419 | M44: =L44 -> 56.785419 | N44: =M44 -> 56.785419 | O44: =N44 -> 56.785419 | P44: =O44 -> 56.785419
B46: Other Current Assets | F46: =Sheet3!C13 -> 14.736 | G46: =Sheet3!D13 -> 26.059 | H46: =Sheet3!E13 -> 52.519 | I46: =Sheet3!F13 -> 82.046 | J46: 0 | K46: =Sheet3!H13 -> 119.323 | L46: =L47*L8 -> 187.40248 | M46: =M47*M8 -> 238.75208 | N46: =N47*N8 -> 295.927 | O46: =O47*O8 -> 357.01658 | P46: =P47*P8 -> 414.15441
B47: % of sales | F47: =F46/F$8 -> 0.12293831 | G47: =G46/G$8 -> 0.10427562 | H47: =H46/H$8 -> 0.12260911 | I47: =I46/I$8 -> 0.125741 | J47: =J46/J$8 -> 0 | K47: =K46/K$8 -> 0.095519533 | L47: =AVERAGE(F47:I47,K47) -> 0.11421671 | M47: =L47 -> 0.11421671 | N47: =M47 -> 0.11421671 | O47: =N47 -> 0.11421671 | P47: =O47 -> 0.11421671
B49: Total Current Assets | F49: =SUM(F40,F43,F46) -> 65.465 | G49: =SUM(G40,G43,G46) -> 81.981 | H49: =SUM(H40,H43,H46) -> 167.573 | I49: =SUM(I40,I43,I46) -> 245.484 | J49: =SUM(J40,J43,J46) -> 184.067 | K49: =SUM(K40,K43,K46) -> 392.25 | L49: =SUM(L40,L43,L46) -> 543.29447 | M49: =SUM(M40,M43,M46) -> 691.83577 | ... P49: =SUM(P40,P43,P46) -> 1194.4607
B51: Accounts Payable | F51: =Sheet3!C34 -> 36.328 | G51: =Sheet3!D34 -> 46.52 | H51: =Sheet3!E34 -> 113.647 | I51: =Sheet3!F34 -> 119.998 | J51: =Sheet3!G34 -> 144.786 | K51: =Sheet3!H34 -> 182.436 | L51: =L52*L11/365 -> 262.1467 | M51: =M52*M11/365 -> 332.49896 | N51: =N52*N11/365 -> 406.62885 | O51: =O52*O11/365 -> 486.15157 | P51: =P52*P11/365 -> 551.13928
B52: DPO | F52: =F51/F11*365 -> 274.43745 | G52: =G51/G11*365 -> 225.25604 | H52: =H51/H11*365 -> 351.11863 | I52: =I51/I11*365 -> 252.96295 | J52: =J51/J11*365 -> 225.53106 | K52: =K51/K11*365 -> 235.31977 | L52: =AVERAGE(G52:K52) -> 258.03769 | M52: =L52 -> 258.03769 | N52: =M52 -> 258.03769 | O52: =N52 -> 258.03769 | P52: =O52 -> 258.03769
B54: Other Current Liabilities | F54: =Sheet3!C42 -> 94.391 | G54: =Sheet3!D42 -> 143.109 | H54: =Sheet3!E42 -> 203.185 | I54: =Sheet3!F42 -> 300.113 | J54: =Sheet3!G42 -> 426.369 | K54: =Sheet3!H42 -> 563.254 | L54: =L55*L8 -> 754.76139 | M54: =M55*M8 -> 961.57131 | N54: =N55*N8 -> 1191.8427 | O54: =O55*O8 -> 1437.8803 | P54: =P55*P8 -> 1668.0022
B55: % of Sales | F55: =F54/F$8 -> 0.78747758 | G55: =G54/G$8 -> 0.57265361 | H55: =H54/H$8 -> 0.47434895 | I55: =I54/I$8 -> 0.4599433 | J55: =J54/J$8 -> 0.45484212 | K55: =K54/K$8 -> 0.45089177 | L55: =AVERAGE(H55:K55) -> 0.46000653 | M55: =L55 -> 0.46000653 | N55: =M55 -> 0.46000653 | O55: =N55 -> 0.46000653 | P55: =O55 -> 0.46000653
B57: Total Current Liabilities | F57: =F51+F54 -> 130.719 | G57: =G51+G54 -> 189.629 | H57: =H51+H54 -> 316.832 | I57: =I51+I54 -> 420.111 | J57: =J51+J54 -> 571.155 | K57: =K51+K54 -> 745.69 | L57: =L51+L54 -> 1016.9081 | M57: =M51+M54 -> 1294.0703 | ... P57: =P51+P54 -> 2219.1415
B59: Net Working Capital | F59: =F49-F57 -> -65.254 | G59: =G49-G57 -> -107.648 | H59: =H49-H57 -> -149.259 | I59: =I49-I57 -> -174.627 | J59: =J49-J57 -> -387.088 | K59: =K49-K57 -> -353.44 | L59: =L49-L57 -> -473.61362 | M59: =M49-M57 -> -602.23451 | ... P59: =P49-P57 -> -1024.6808
B60: changes in NWC | G60: =G59-F59 -> -42.394 | H60: =H59-G59 -> -41.611 | I60: =I59-H59 -> -25.368 | J60: =J59-I59 -> -212.461 | K60: =K59-J59 -> 33.648 | L60: =L59-K59 -> -120.17362 | M60: =M59-L59 -> -128.62089 | N60: =N59-M59 -> -139.93381 | ... P60: =P59-O59 -> -132.75024
B63: Capex | F63: =-Sheet4!C24 -> 29.99 | G63: =-Sheet4!D24 -> 32.102 | H63: =-Sheet4!E24 -> 19.353 | I63: =-Sheet4!F24 -> 33.24 | J63: =-Sheet4!G24 -> 10.953 | K63: =-Sheet4!H24 -> 20.177 | L63: =L64*L8 -> 50.847136 | M63: =M64*M8 -> 64.779608 | N63: =N64*N8 -> 80.292643 | O63: =O64*O8 -> 96.867824 | P63: =P64*P8 -> 112.37079
B64: % of Sales | F64: =F63/F8 -> 0.25019814 | G64: =G63/G8 -> 0.12845681 | H64: =H63/H8 -> 0.045180871 | I64: =I63/I8 -> 0.050942529 | J64: =J63/J8 -> 0.011684446 | K64: =K63/K8 -> 0.016151937 | L64: =AVERAGE(H64:K64) -> 0.030989946 | M64: =L64 -> 0.030989946 | N64: =M64 -> 0.030989946 | O64: =N64 -> 0.030989946 | P64: =O64 -> 0.030989946
B66: Depreciation | F66: =Sheet4!C8 -> 4.32 | G66: =Sheet4!D8 -> 10.738 | H66: =Sheet4!E8 -> 10.388 | I66: =Sheet4!F8 -> 11.768 | J66: =Sheet4!G8 -> 15.526 | K66: =Sheet4!H8 -> 20.649 | L66: =L67*L63 -> 42.351848 | M66: =M67*M63 -> 53.956551 | N66: =N67*N63 -> 66.877745 | O66: =O67*O63 -> 80.683627 | P66: =P67*P63 -> 93.596436
B67: %Capex | F67: =F66/F63 -> 0.14404802 | G67: =G66/G63 -> 0.33449629 | H67: =H66/H63 -> 0.53676433 | I67: =I66/I63 -> 0.35403129 | J67: =J66/J63 -> 1.4175112 | K67: =K66/K63 -> 1.023393 | L67: =AVERAGE(H67:K67) -> 0.83292494 | M67: =L67 -> 0.83292494 | N67: =M67 -> 0.83292494 | O67: =N67 -> 0.83292494 | P67: =O67 -> 0.83292494
B70: EBIT | F70: =F26 -> -219.609 | G70: =G26 -> -177.147 | H70: =H26 -> -76.975 | I70: =I26 -> -141.159 | J70: =J26 -> 1.27 | K70: =K26 -> 113.552 | L70: =L26 -> 195.25072 | M70: =M26 -> 273.8349 | ... P70: =P26 -> 649.06121
B72: NOPAT | F72: =F70-F33 -> -219.949 | G72: =G70-G33 -> -177.234 | H72: =H70-H33 -> -78.149 | I72: =I70-I33 -> -144.746 | J72: =J70-J33 -> -2.073 | K72: =K70-K33 -> 109.059 | L72: =L70-L33 -> 185.48818 | M72: =M70-M33 -> 260.14315 | ... P72: =P70-P33 -> 616.60815
B73: (+) Depreciation | F73: =F66 -> 4.32 | G73: =G66 -> 10.738 | H73: =H66 -> 10.388 | I73: =I66 -> 11.768 | J73: =J66 -> 15.526 | K73: =K66 -> 20.649 | L73: =L66 -> 42.351848 | M73: =M66 -> 53.956551 | ... P73: =P66 -> 93.596436
B74: (-) Change in NWC | F74: =F60 -> 0 | G74: =G60 -> -42.394 | H74: =H60 -> -41.611 | I74: =I60 -> -25.368 | J74: =J60 -> -212.461 | K74: =K60 -> 33.648 | L74: =L60 -> -120.17362 | M74: =M60 -> -128.62089 | ... P74: =P60 -> -132.75024
B75: (-) Capex | F75: =F63 -> 29.99 | G75: =G63 -> 32.102 | H75: =H63 -> 19.353 | I75: =I63 -> 33.24 | J75: =J63 -> 10.953 | K75: =K63 -> 20.177 | L75: =L63 -> 50.847136 | M75: =M63 -> 64.779608 | ... P75: =P63 -> 112.37079
B77: UFCF | F77: =F72+F73-F74-F75 -> -245.619 | G77: =G72+G73-G74-G75 -> -156.204 | H77: =H72+H73-H74-H75 -> -45.503 | I77: =I72+I73-I74-I75 -> -140.85 | J77: =J72+J73-J74-J75 -> 214.961 | K77: =K72+K73-K74-K75 -> 75.883 | L77: =L72+L73-L74-L75 -> 297.16651 | M77: =M72+M73-M74-M75 -> 377.94099 | ... P77: =P72+P73-P74-P75 -> 730.58404

Sheet WACC
B3: WACC | M3: Total Debt/ | O3: Beta to
I4: Company | K4: Fiscal | L4: Enterprise | M4: Total | N4: EV/SALES | O4: Loc Indx
B5: Cost of Equity | I5: Name | J5: Ticker | K5: Period | L5: Value | M5: Equity (%) | N5: NTM (x) | O5: 5 Year | P5: Unlevered Beta | Q5: Relevered Beta
B6: Risk Free Rate | C6: 0.0425 | I6: Samsara A | J6: IOT-US | K6: 08/02/2025 | L6: 21586.514 | M6: 0.06353286 | N6: 12.340815 | O6: 1.813152 | P6: =O6/(1+(0.75*0.064)) -> 1.7301069 | Q6: =P12*(1+(1-0.21)*M12) -> 1.9724952
B7: Levered Beta | C7: 1.63 | I7: Snowflake | J7: SNOW-US | K7: 07/31/2025 | L7: 89036.859 | M7: 1.134736 | N7: 18.597484 | O7: 1.53532 | P7: =O7/(1+(1-0.21)*M7) -> 0.80957945
B8: Market Risk Premium | C8: 0.0418 | I8: ServiceNow | J8: NOW-US | K8: 09/30/2025 | L8: 181596.56 | M8: 0.21254756 | N8: 12.086945 | O8: 1.505298 | P8: =O8/(1+(1-0.21)*M8) -> 1.288879
B9: Cost of Equity | C9: =C6+C7*C8 -> 0.110634 | I9: Zscaler | J9: ZS-US | K9: 07/2025 | L9: 50194.328 | M9: 0.99850106 | N9: 15.446996 | O9: 1.855119 | P9: =O9/(1+(1-0.21)*M9) -> 1.0370654
I10: Cloudflare A | J10: NET-US | K10: 09/30/2025 | L10: 81039.266 | M10: 2.5996358 | N10: 32.441214 | O10: 2.437837 | P10: =O10/(1+(1-0.21)*M10) -> 0.79831915
B11: Cost of Debt | I11: monday.com | J11: MNDY-US | K11: 06/30/2025 | L11: 8258.0928 | M11: 0.10584898 | N11: 5.908907 | O11: 2.123528 | P11: =O11/(1+(1-0.21)*M11) -> 1.9596599
B12: Yield of Debt | C12: 0.0558 | I12: Average | M12: 0.85246703 | N12: 16.13706 | O12: 1.878376 | P12: =AVERAGE(P7:P11) -> 1.1787006
B13: Tax Rate | C13: 0.21 | I13: Median | M13: 0.60552431 | N13: 13.893905 | O13: 1.834135 | P13: =MEDIAN(P7:P12) -> 1.107883
B14: After Tax Cost of Debt | C14: 0.0441
B16: Capital Structure
B17: Total Debt/ Total Capital | C17: 0.0566
B18: Total Equity/Total Capital | C18: =1-C17 -> 0.9434
B20: WACC | C20: =C18*C9+C17*C14 -> 0.10686818
B21: FS | C21: 0.1155

Sheet DCF
B2: Samsara
B3: NASDAQ: IOT | H3: Historicals | N3: Projected
E4: Date | F4: FY20 | G4: FY21 | H4: FY22 | I4: FY23 | J4: FY24 | K4: FY25 | L4: FY26E | M4: FY27E | N4: FY28E | O4: FY29E | P4: FY30E
C6: UFCF | F6: ='Operating Model'!F77 -> -245.619 | G6: ='Operating Model'!G77 -> -156.204 | H6: ='Operating Model'!H77 -> -45.503 | I6: ='Operating Model'!I77 -> -140.85 | J6: ='Operating Model'!J77 -> 214.961 | K6: ='Operating Model'!K77 -> 75.883 | L6: ='Operating Model'!L77 -> 297.16651 | M6: ='Operating Model'!M77 -> 377.94099 | ... P6: ='Operating Model'!P77 -> 730.58404
C7: Period | L7: 1 | M7: 2 | N7: 3 | O7: 4 | P7: 5
C8: Discount Factor | L8: =1/((1+WACC!$C$20)^DCF!L7) -> 0.90344995 | M8: =1/((1+WACC!$C$20)^DCF!M7) -> 0.81622182 | N8: =1/((1+WACC!$C$20)^DCF!N7) -> 0.73741556 | O8: =1/((1+WACC!$C$20)^DCF!O7) -> 0.66621805 | P8: =1/((1+WACC!$C$20)^DCF!P7) -> 0.60189467
C9: PV of UFCF | L9: =L8*L6 -> 268.47507 | M9: =M8*M6 -> 308.48368 | N9: =N8*N6 -> 365.55592 | O9: =O8*O6 -> 415.41657 | P9: =P8*P6 -> 439.73464
C12: Terminal Value: Exit Multiple Method
C13: Exit Multiple | D13: 14x
C14: Terminal Revenue | D14: ='Operating Model'!P8 -> 3626.0403
C15: Terminal Value | D15: =14*D14 -> 50764.564
C16: Discounted TV | D16: =D15/(1+WACC!C20)^5 -> 30554.92
C17: Enterprise Value | D17: =D16+SUM(L9:P9) -> 32352.586
C18: (-) Debt | D18: =Sheet3!H47 -> 64.622
C19: (+) Cash | D19: =Sheet3!H7 -> 694.798
C20: Equity Value | D20: =D17-D18+D19 -> 32982.762
C21: Shares Outstanding | D21: 599.09
C22: Implied Share Price | D22: =D20/D21 -> 55.05477
C23: Current Share Price | D23: 24.5
C24: Implied Upside | D24: =D22/D23-1 -> 1.2471335

Sheet Multiple Periods
A1: Samsara Inc- Company Financial (Multiple Periods)
A2: IOT US Equity Periodicity:A Currency:USD Estimate Source:BST Actual Source:Bloomberg
A3: In Millions of USD | E3: 2018 A (Rep) | F3: 2019 A (Rep) | G3: 2020 A (Rep) | H3: 2021 A (Rep) | I3: 2022 A (Rep) | J3: 2023 A (Rep) | K3: 2024 A (Rep) | L3: 2025 A (Rep) | M3: 2026 A (Fwd) | N3: 2027 A (Fwd)
A4: 12 Months Ending | B4: Field Expression | C4: Calcrt Field | D4: Segment Id | E4: 43130 | F4: 43495 | G4: 43862 | H4: 44226 | I4: 44590 | J4: 44954 | K4: 45325 | L4: 45689 | M4: 46053 | N4: 46417
A5: Highlights
A6: Adjusted Diluted EPS | B6: IS_COMP_EPS_ADJUSTED_OLD | C6: IS900 | I6: -0.42 | J6: -0.13 | K6: 0.07 | L6: 0.26 | M6: 0.46777778 | N6: 0.56105263
A7: Revenue | B7: IS_COMP_SALES | C7: IS902 | G7: 119.865 | H7: 249.905 | I7: 428.345 | J7: 652.545 | K7: 937.4 | L7: 1249.199 | M7: 1577.0556 | N7: 1900.6316
O8: =J7/J9 -> 0.8207566 | P8: =K7/K9 -> 0.85064988 | Q8: =L7/L9 -> 0.85686643 | R8: =M7/M9 -> 0.85947266 | S8: =N7/N9 -> 0.85567274
A9: Annualized Recurring Revenue | B9: IS_ANNUALIZED_RECURRING_REV | C9: IM696 | G9: 194 | H9: 341 | I9: 558 | J9: 795.053 | K9: 1101.981 | L9: 1457.869 | M9: 1834.9107 | N9: 2221.2132 | O9: =I7/H9 -> 1.2561437 | P9: =J7/I9 -> 1.1694355 | Q9: =K7/J9 -> 1.1790409 | R9: =L7/K9 -> 1.133594 | S9: =M7/L9 -> 1.081754
A11: Adjusted Gross Margin (%) | B11: IS_COMP_GROSS_MARGIN_PERCENTAGE | C11: IM092 | I11: 72 | J11: 73 | K11: 75 | L11: 77 | M11: 77.468031 | N11: 77.348724
A12: Adjusted Operating Income | B12: IS_COMPARABLE_EBIT | C12: IM132 | I12: -114.078 | J12: -76.975 | K12: 1.27 | L12: 113.552 | M12: 235.88235 | N12: 306
A13: Operating Margin (%) | B13: ADJ_OPERATING_MARGIN | C13: RX609 | G13: -183.21362 | H13: -70.885737 | I13: -26.542623 | J13: -11.796121 | K13: 0.13548329 | L13: 9.0899849 | M13: 14.941852 | N13: 15.962708
A15: Company Operating Metrics
A16: Company-Level Industry Statistics
A17: Annualized Recurring Revenue (ARR) | B17: IS_ANNUALIZED_RECURRING_REV | C17: IM696 | G17: 194 | H17: 341 | I17: 558 | J17: 795.053 | K17: 1101.981 | L17: 1457.869 | M17: 1834.9107 | N17: 2221.2132
A18: $100k+ in ARR | B18: IS_ANNUALIZED_RECURRING_REV | C18: IM696 | D18: SEG0000857764 Segment | M18: 1096.7412 | N18: 1333.0958
A19: Percent of ARR | B19: CB_IS_RECUR_REV | C19: IC934 | D19: SEG0000857764 Segment | I19: 45 | J19: 48 | K19: 52 | L19: 48 | M19: 58.425708 | N19: 59.804406
A20: Existing $100k+ in ARR | B20: IS_ANNUALIZED_RECURRING_REV | C20: IM696 | D20: SEG2122315175 Segment
A21: New $100K+ ARR | B21: IS_ANNUALIZED_RECURRING_REV | C21: IM696 | D21: SEG7233412516 Segment
A22: ARR from <$100k | B22: IS_ANNUALIZED_RECURRING_REV | C22: IM696 | D22: SEG1439748622 Segment
A23: Existing <$100K ARR | B23: IS_ANNUALIZED_RECURRING_REV | C23: IM696 | D23: SEG9217553926 Segment
A24: New <$100K ARR | B24: IS_ANNUALIZED_RECURRING_REV | C24: IM696 | D24: SEG4106456585 Segment
A25: Net New ARR | B25: IS_NET_RECURRING_REV_ADDTN | C25: IL313 | H25: 147 | I25: 217 | J25: 237.1 | K25: 1102 | L25: 1460 | M25: 376.94233 | N25: 386.86711
A26: New | B26: IS_NET_RECURRING_REV_ADDTN | C26: IL313 | D26: SEG5581076398 Segment | M26: 160.86449 | N26: 147.78784
A27: Existing | B27: IS_NET_RECURRING_REV_ADDTN | C27: IL313 | D27: SEG9469979050 Segment | M27: 212.77641 | N27: 255.02599
A29: Annualized Recurring Revenue | B29: IS_ANNUALIZED_RECURRING_REV | C29: IM696 | G29: 194 | H29: 341 | I29: 558 | J29: 795.053 | K29: 1101.981 | L29: 1457.869 | M29: 1834.9107 | N29: 2221.2132
A30: Core | B30: IM969 | C30: IM969 | D30: SEG3789147034 Segment
A31: New | B31: IS_ANNUALIZED_RECURRING_REV | C31: IM696 | D31: SEG5469359577 Segment
A33: Annualized Recurring Revenue
A34: Existing | B34: IS_ANNUALIZED_RECURRING_REV | C34: IM696 | D34: SEG9469979050 Segment
A35: $100k+ in ARR | B35: IS_ANNUALIZED_RECURRING_REV | C35: IM696 | D35: SEG2122315175 Segment
A36: New | B36: IS_ANNUALIZED_RECURRING_REV | C36: IM696 | D36: SEG5581076398 Segment | M36: 157.415 | N36: 102.8
A37: $100K+ ARR | B37: IS_ANNUALIZED_RECURRING_REV | C37: IM696 | D37: SEG7233412516 Segment
A39: Annualized Recurring Revenue Per User | B39: CB_IS_ANN_RECUR_REV_PER_USER | C39: IC983
A40: $100k+ in ARR | B40: CB_IS_ANN_RECUR_REV_PER_USER | C40: IC983 | D40: SEG0000857764 Segment | M40: 341328.78 | N40: 349406.83
A42: Annualized Recurring Revenue Per User
A43: Core | B43: CB_IS_ANN_RECUR_REV_PER_USER | C43: IC983 | D43: SEG3789147034 Segment
A44: New | B44: CB_IS_ANN_RECUR_REV_PER_USER | C44: IC983 | D44: SEG5469359577 Segment
A46: Net Retention Rate | B46: CORE_CLIENT_RETENTION_RATE | C46: M4278
A48: Net Revenue Retention Rate Percentage | B48: NET_REV_RETENTION_RATE_PCT | C48: M1269 | M48: 114.74533 | N48: 113.58934
A49: $100k+ in ARR | B49: NET_REV_RETENTION_RATE_PCT | C49: M1269 | D49: SEG0000857764 Segment
A50: ARR from <$100k | B50: NET_REV_RETENTION_RATE_PCT | C50: M1269 | D50: SEG1439748622 Segment
A52: Number of Customers
A53: $1M+ in ARR | B53: NUMBER_OF_CUSTOMERS | C53: M6307 | D53: SEG0000857765 Segment | I53: 0.031 | J53: 0.051 | K53: 0.082 | M53: -0.118
A54: Net Adds | B54: CB_NET_PAID_SUBSCRIBER_ADDTNS | C54: M6920 | D54: SEG0000857765 Segment
A55: $100k+ in ARR | B55: NUMBER_OF_CUSTOMERS | C55: M6307 | D55: SEG0000857764 Segment | I55: 0.806 | J55: 1.237 | K55: 1.848 | L55: 2.506 | M55: 3.13486 | N55: 3.7765006
A56: Net Adds | B56: CB_NET_PAID_SUBSCRIBER_ADDTNS | C56: M6920 | D56: SEG0000857764 Segment | M56: 0.63440667 | N56: 0.64059373
A57: $10K-100K in ARR | B57: NUMBER_OF_CUSTOMERS | C57: M6307 | D57: SEG5775215220 Segment | I57: 8.9 | J57: 12.5 | K57: 16.5
A58: Net Adds | B58: CB_NET_PAID_SUBSCRIBER_ADDTNS | C58: M6920 | D58: SEG5775215220 Segment
A59: ARR from <$100k | B59: NUMBER_OF_CUSTOMERS | C59: M6307 | D59: SEG1439748622 Segment
A60: Net Adds | B60: CB_NET_PAID_SUBSCRIBER_ADDTNS | C60: M6920 | D60: SEG1439748622 Segment
A61: $5k-$10k in ARR | B61: NUMBER_OF_CUSTOMERS | C61: M6307 | D61: SEG1135819755 Segment | I61: 14.5 | J61: 19.3 | K61: 24.4
A62: $5k-$10k in ARR | B62: CB_NET_PAID_SUBSCRIBER_ADDTNS | C62: M6920 | D62: SEG1135819755 Segment
A63: <$5k in ARR | B63: NUMBER_OF_CUSTOMERS | C63: M6307 | D63: SEG2220347974 Segment
A64: Net Adds | B64: CB_NET_PAID_SUBSCRIBER_ADDTNS | C64: M6920 | D64: SEG2220347974 Segment
A66: Percentage of ARR Core Customers
A67: $100k+ in ARR | B67: CB_IS_RECUR_REV | C67: IC934 | D67: SEG0000857764 Segment | I67: 45 | J67: 48 | K67: 52 | L67: 48 | M67: 58.425708 | N67: 59.804406
A68: $10K-100K in ARR | B68: CB_IS_RECUR_REV | C68: IC934 | D68: SEG5775215220 Segment | I68: 41 | J68: 41 | K68: 39 | L68: 38
A69: <$10K in ARR | B69: CB_IS_RECUR_REV | C69: IC934 | D69: SEG9664117872 Segment | L69: 7 | M69: 5.55 | N69: 4.95
A70: $5k-$10k in ARR | B70: CB_IS_RECUR_REV | C70: IC934 | D70: SEG1135819755 Segment | I70: 7 | J70: 6 | K70: 5
A71: <$5k in ARR | B71: CB_IS_RECUR_REV | C71: IC934 | D71: SEG2220347974 Segment | I71: 7 | J71: 5 | K71: 3
A73: Billings | B73: SOFTWARE_BILLINGS_RATIO | C73: F1118 | H73: 285.06 | I73: 492.301 | J73: 765.379 | K73: 1076.32 | L73: 1578.283 | M73: 1716.597 | N73: 2067.4621
A74: Deferred Revenue | B74: DEFERRED_REV | C74: FS167 | H74: 249.572 | I74: 313.686 | J74: 426.565 | K74: 565.486 | L74: 685.77 | M74: 797.04387 | N74: 929.89182
A75: Change in Deferred Revenue | B75: CF_CHG_IN_DEFER_UNEARND_REV_ST | C75: CF434 | G75: 95.422 | H75: 35.16 | I75: 64.001 | J75: 112.879 | K75: 138.92 | L75: 120.283 | M75: 114.36236 | N75: 144.40398
A76: Remaining Performance Obligation | B76: BS_REMAINING_PERFORMANCE_OBLIG | C76: BL016 | G76: 538.8 | H76: 779.1 | I76: 1055.5 | J76: 1450.8 | K76: 2001.2 | L76: 2651.2
A77: Current Remaining Performance Obligation | B77: CB_BS_REMAIN_PERFORM_OBLIG_DUE_IN_1_YR | C77: BL700 | H77: 326.6 | I77: 499.7 | J77: 694.8 | K77: 948.1 | L77: 1253.8
A78: Noncurrent Remaining Performance Obligation | B78: CB_BS_REMAINI_PERFORM_OBLIG_DUE_BEYOND_1_YR | C78: BL701 | G78: 538.8 | H78: 452.5 | I78: 555.8 | J78: 756 | K78: 1053.1 | L78: 1397.4
A79: Selling, General & Administrative Expense | B79: IS_SG_AND_A_EXPENSE | C79: IM122 | G79: 228.895 | H79: 277.485 | I79: 451.052 | J79: 540.883 | K79: 681.692 | L79: 836.257 | M79: 975.52854 | N79: 1132.7405
A80: Days Sales Outstanding | B80: ANNUALIZED_DAYS_SALES_OUTSTDG | C80: F0837 | G80: 104.75261 | H80: 61.536472 | I80: 69.671102 | J80: 68.537171 | K80: 64.048986 | L80: 68.189155 | M80: 75.632687 | N80: 101.0374
A81: Inventory Turnover | B81: CB_INVENTORY_TURNOVER_DAY | C81: M6124
A82: Current Ratio | B82: CUR_RATIO | C82: RR053 | G82: 1.8716838 | H82: 2.3175633 | I82: 3.2522474 | J82: 2.1655947 | K82: 1.4987057 | L82: 1.5041177 | M82: 1.88971 | N82: 2.1824733
A83: Days Inventory Outstanding | B83: ANNUALIZED_DAYS_INV_OUTSTDG | C83: F0838 | G83: 125.43711 | H83: 66.018543 | I83: 96.690241 | J83: 80.850583 | K83: 33.397689 | L83: 47.47773 | M83: 41.953051 | N83: 45.741278
A84: Days Payable Outstanding | B84: ACCOUNTS_PAYABLE_TURNOVER_DAYS | C84: RR774 | H84: 89.975245 | I84: 93.740556 | J84: 81.208025 | K84: 61.989066 | L84: 63.728947
A86: Business Breakdown
A87: Revenue
A88: Subscription | B88: SALES_REV_TURN | C88: IS010 | D88: SEG0000586646 Segment | G88: 116.992 | H88: 245.481 | I88: 418.98 | J88: 639.533 | K88: 919.362 | L88: 1225.777 | M88: 1567.5549 | N88: 1888.2354
A89: Other Product | B89: SALES_REV_TURN | C89: IS010 | D89: SEG0000586647 Segment | G89: 2.873 | H89: 4.424 | I89: 9.365 | J89: 13.012 | K89: 18.023 | L89: 23.422 | M89: 32.086748 | N89: 41.741956
A91: Product Breakdown
A92: Annualized Recurring Revenue (ARR) | B92: IS_ANNUALIZED_RECURRING_REV | C92: IM696 | G92: 194 | H92: 341 | I92: 558 | J92: 795.053 | K92: 1101.981 | L92: 1457.869 | M92: 1834.9107 | N92: 2221.2132
A93: Telematics | B93: IS_ANNUALIZED_RECURRING_REV | C93: IM696 | D93: SEG2136810916 Segment | M93: 2654.7859
A94: Percent of Recurring Revenue | B94: CB_IS_RECUR_REV | C94: IC934 | D94: SEG2136810916 Segment | M94: 39.420683
A95: Video-based Safety | B95: IS_ANNUALIZED_RECURRING_REV | C95: IM696 | D95: SEG6025713568 Segment
A96: Percent of Recurring Revenue | B96: CB_IS_RECUR_REV | C96: IC934 | D96: SEG6025713568 Segment | M96: 49.349565
A97: All Other | B97: IM969 | C97: IM969 | D97: SEG9914616220 Segment
A98: Percent of Recurring Revenue | B98: CB_IS_RECUR_REV | C98: IC934 | D98: SEG9914616220 Segment | M98: 13.453268 | N98: 15.276689
A100: Net Recurring Revenue - Addition | B100: IS_NET_RECURRING_REV_ADDTN | C100: IL313 | H100: 147 | I100: 217 | J100: 237.1 | K100: 1102 | L100: 1460 | M100: 376.94233 | N100: 386.86711
A101: Telematics | B101: IS_NET_RECURRING_REV_ADDTN | C101: IL313 | D101: SEG2136810916 Segment | M101: 148.1975
A102: Video-based Safety | B102: IS_NET_RECURRING_REV_ADDTN | C102: IL313 | D102: SEG6025713568 Segment | M102: 177.13485 | N102: 191.63367
A103: All Other | B103: IS_NET_RECURRING_REV_ADDTN | C103: IL313 | D103: SEG9914616220 Segment | M103: 71.72868 | N103: 94.970522
A105: Regional Breakdown
A106: Revenue
A107: United States | B107: SALES_REV_TURN | C107: IS010 | D107: SEG0000586640 Segment | G107: 113.664 | H107: 230.479 | I107: 384.24 | J107: 581.755 | K107: 821.885 | L107: 1082.481 | M107: 1009.3044 | N107: 1648.5809
A108: Other Countries | B108: SALES_REV_TURN | C108: IS010 | D108: SEG0000586642 Segment | G108: 6.201 | H108: 19.426 | I108: 44.105 | J108: 70.79 | K108: 115.5 | L108: 166.718 | M108: 158.8566 | N108: 259.47342
A110: Income Statement (Adjusted)
A111: Revenue | B111: IS_COMP_SALES | C111: IS902 | G111: 119.865 | H111: 249.905 | I111: 428.345 | J111: 652.545 | K111: 937.4 | L111: 1249.199 | M111: 1577.0556 | N111: 1900.6316
A113: Cost of Revenue | B113: IS_ADJUSTED_COGS_AS_REPORTED | C113: IM057 | K113: 247.032 | L113: 282.972 | M113: 355.09879 | N113: 429.47397
A114: Gross Profit | B114: IS_ADJ_GROSS_PROFIT_AS_REPORTED | C114: IS923 | G114: 71.549 | H114: 174.525 | I114: 310.205 | J114: 479.355 | K114: 703.078 | L114: 966.227 | M114: 1221.2847 | N114: 1467.7794
A115: Gross Margin (%) | B115: IS_COMP_GROSS_MARGIN_PERCENTAGE | C115: IM092 | I115: 72 | J115: 73 | K115: 75 | L115: 77 | M115: 77.468031 | N115: 77.348724
A117: Total Operating Expenses | B117: CB_IS_ADJUSTED_OPEX | C117: IM744 | M117: 985.66495 | N117: 1164.8521
A118: Research & Development Expense | B118: IS_ADJ_R_AND_D_AS_REPORTED | C118: IS925 | G118: 66.812 | H118: 85.955 | I118: 102.276 | J118: 187.405 | K118: 163.361 | L118: 192.466 | M118: 220.73672 | N118: 263.18028
...

Sheet Sheet1
A2: Samsara Inc (IOT US) - BBG Adjusted
A4: In Millions of USD except Per Share | C4: FY 2020 | D4: FY 2021 | E4: FY 2022 | F4: FY 2023 | G4: FY 2024 | H4: FY 2025 | I4: Last 12M | J4: FY 2026 Est | K4: FY 2027 Est
A5: 12 Months Ending | C5: 02/01/2020 | D5: 01/30/2021 | E5: 01/29/2022 | F5: 01/28/2023 | G5: 02/03/2024 | H5: 02/01/2025 | I5: 08/02/2025 | J5: 01/31/2026 | K5: 01/31/2027
A6: Revenue | B6: SALES_REV_TURN | C6: 119.865 | D6: 249.905 | E6: 428.345 | F6: 652.545 | G6: 937.385 | H6: 1249.199 | I6: 1426.635 | J6: 1577.0556 | K6: 1900.6316
A7: + Sales & Services Revenue | B7: IS_SALES_AND_SERVICES_REVENUES | C7: 116.992 | D7: 245.481 | E7: 418.98 | F7: 639.533 | G7: 919.362 | H7: 1225.777 | I7: 1397.753
A8: + Other Revenue | B8: IS_OTHER_REVENUE | C8: 2.873 | D8: 4.424 | E8: 9.365 | F8: 13.012 | G8: 18.023 | H8: 23.422 | I8: 28.882
A9: - Cost of Revenue | B9: IS_COGS_TO_FE_AND_PP_AND_G | C9: 48.322 | D9: 75.393 | E9: 124.484 | F9: 182.656 | G9: 247.032 | H9: 298.321 | I9: 330.001
A10: + Cost of Goods & Services | B10: IS_COG_AND_SERVICES_SOLD | C10: 48.322 | D10: 75.393 | E10: 124.484 | F10: 182.656 | G10: 247.032 | H10: 298.321 | I10: 330.001
A11: Gross Profit | B11: GROSS_PROFIT | C11: 71.543 | D11: 174.512 | E11: 303.861 | F11: 469.889 | G11: 690.353 | H11: 950.878 | I11: 1096.634 | J11: 1221.7134 | K11: 1470.1195
A12: + Other Operating Income | B12: IS_OTHER_OPER_INC | C12: 0 | D12: 0 | E12: 0 | F12: 0 | G12: 0 | H12: 0 | I12: 0
A13: - Operating Expenses | B13: IS_OPERATING_EXPN | C13: 299.361 | D13: 377.223 | E13: 656.177 | F13: 728.288 | G13: 940.273 | H13: 1135.973 | I13: 1217.412
A14: + Selling, General & Admin | B14: IS_SGA_EXPENSE | C14: 228.895 | D14: 277.485 | E14: 451.052 | F14: 540.883 | G14: 681.692 | H14: 836.257 | I14: 898.291
A15: + Selling & Marketing | B15: IS_SELLING_EXPENSES | C15: 181.556 | D15: 202.262 | E15: 291.209 | F15: 370.098 | G15: 486.649 | H15: 601.648 | I15: 642.201
A16: + General & Administrative | B16: IS_GENERAL_AND_ADMINISTRATIVE | C16: 47.339 | D16: 75.223 | E16: 159.843 | F16: 170.785 | G16: 195.043 | H16: 234.609 | I16: 256.09
A17: + Research & Development | B17: IS_OPERATING_EXPENSES_RD | C17: 70.466 | D17: 99.738 | E17: 205.125 | F17: 187.405 | G17: 258.581 | H17: 299.716 | I17: 319.121
A18: + Other Operating Expense | B18: IS_OTHER_OPERATING_EXPENSES | C18: 0 | D18: 0 | E18: 0 | F18: 0 | G18: 0 | H18: 0 | I18: 0
A19: Operating Income (Loss) | B19: IS_OPER_INC | C19: -227.818 | D19: -202.711 | E19: -352.316 | F19: -258.399 | G19: -249.92 | H19: -185.095 | I19: -120.778 | J19: 235.882 | K19: 306
A20: - Non-Operating (Income) Loss | B20: IS_NONOP_INCOME_LOSS | C20: -2.934 | D20: 0.642 | E20: 0.002 | F20: -15.62 | G20: -39.964 | H20: -39.559 | I20: -43.998
A21: + Foreign Exch (Gain) Loss | B21: IS_FOREIGN_EXCH_LOSS | C21: 0 | D21: 0 | E21: 0 | F21: 0 | G21: 0 | H21: 0
A22: + Other Non-Op (Income) Loss | B22: IS_OTHER_NON_OPERATING_INC_LOSS | C22: -2.934 | D22: 0.642 | E22: 0.002 | F22: -15.62 | G22: -39.964 | H22: -39.559 | I22: -43.998
A23: Pretax Income (Loss), Adjusted | B23: PRETAX_INC | C23: -224.884 | D23: -203.353 | E23: -352.318 | F23: -242.779 | G23: -209.956 | H23: -145.536 | I23: -76.78 | J23: -35.26 | K23: 105.514
A24: - Abnormal Losses (Gains) | B24: IS_ABNORMAL_ITEM | C24: 0 | D24: 6.768 | E24: 1.532 | F24: 1.056 | G24: 73.427 | H24: 4.878 | I24: 4.878
A25: + Legal Settlement | B25: IS_LEGAL_LITIGATION_SETTLEMENT | C25: — | D25: — | E25: — | F25: — | G25: 68.665 | H25: 0.85
A26: + Other Abnormal Items | B26: IS_OTHER_ONE_TIME_ITEMS | C26: — | D26: 6.768 | E26: 1.532 | F26: 1.056 | G26: 4.762 | H26: 4.028
A27: Pretax Income (Loss), GAAP | B27: PRETAX_INC | C27: -224.884 | D27: -210.121 | E27: -353.85 | F27: -243.835 | G27: -283.383 | H27: -150.414 | I27: -81.658 | J27: -35.26 | K27: 105.514
A28: - Income Tax Expense (Benefit) | B28: IS_INC_TAX_EXP | C28: 0.34 | D28: 0.087 | E28: 1.174 | F28: 3.587 | G28: 3.343 | H28: 4.493 | I28: 6.271
A29: + Current Income Tax | B29: IS_CURRENT_INCOME_TAX_BENEFIT | C29: 0.34 | D29: 0.387 | E29: 0.135 | F29: 1.592 | G29: 2.412 | H29: 2.42
A30: + Deferred Income Tax | B30: IS_DEFERRED_INCOME_TAX_BENEFIT | C30: 0 | D30: -0.3 | E30: 1.039 | F30: 1.995 | G30: 0.931 | H30: 2.073
A31: Income (Loss) from Cont Ops | B31: IS_INC_BEF_XO_ITEM | C31: -225.224 | D31: -210.208 | E31: -355.024 | F31: -247.422 | G31: -286.726 | H31: -154.907 | I31: -87.929 | J31: -60.073 | K31: -4.113
A32: - Net Extraordinary Losses (Gains) | B32: XO_GL_NET_OF_TAX | C32: 0 | D32: 0 | E32: 0 | F32: 0 | G32: 0 | H32: 0 | I32: 0
A33: + Discontinued Operations | B33: IS_DISCONTINUED_OPERATIONS | C33: 0 | D33: 0 | E33: 0 | F33: 0 | G33: 0 | H33: 0 | I33: 0
A34: + XO & Accounting Changes | B34: EXTRAORD_ITEMS_ACCOUNTING_CHANGS | C34: 0 | D34: 0 | E34: 0 | F34: 0 | G34: 0 | H34: 0 | I34: 0
A35: Income (Loss) Incl. MI | B35: NI_INCLUDING_MINORITY_INT_RATIO | C35: -225.224 | D35: -210.208 | E35: -355.024 | F35: -247.422 | G35: -286.726 | H35: -154.907 | I35: -87.929
A36: - Minority Interest | B36: MIN_NONCONTROL_INTEREST_CREDITS | C36: 0 | D36: 0 | E36: 0 | F36: 0 | G36: 0 | H36: 0 | I36: 0
A37: Net Income, GAAP | B37: NET_INCOME | C37: -225.224 | D37: -210.208 | E37: -355.024 | F37: -247.422 | G37: -286.726 | H37: -154.907 | I37: -87.929 | J37: -60.073 | K37: -4.113
A38: - Preferred Dividends | B38: IS_TOT_CASH_PFD_DVD | C38: 0 | D38: 0 | E38: 0 | F38: 0 | G38: 0 | H38: 0 | I38: 0
A39: - Other Adjustments | B39: OTHER_ADJUSTMENTS | C39: 0 | D39: 0 | E39: 0 | F39: 0 | G39: 0 | H39: 0 | I39: 0
A40: Net Income Avail to Common, GAAP | B40: EARN_FOR_COMMON | C40: -225.224 | D40: -210.208 | E40: -355.024 | F40: -247.422 | G40: -286.726 | H40: -154.907 | I40: -87.929 | J40: -60.073 | K40: -4.113
A42: Net Income Avail to Common, Adj | B42: EARN_FOR_COMMON | C42: -225.224 | D42: -204.8613 | E42: -353.8137 | F42: -246.5878 | G42: -228.7187 | H42: -150.029 | I42: -83.80889 | J42: 272.611 | K42: 336.889
A43: Net Abnormal Losses (Gains) | B43: IS_NET_ABNORMAL_ITEMS | C43: 0 | D43: 5.3467 | E43: 1.2103 | F43: 0.8342 | G43: 58.0073 | H43: 4.878 | I43: 4.12011
A44: Net Extraordinary Losses (Gains) | B44: XO_GL_NET_OF_TAX | C44: 0 | D44: 0 | E44: 0 | F44: 0 | G44: 0 | H44: 0 | I44: 0
A46: Basic Weighted Avg Shares | B46: IS_AVG_NUM_SH_FOR_EPS | C46: 230.4269 | D46: 239.2817 | E46: 277.5435 | F46: 514.2792 | G46: 534.8785 | H46: 556.3174 | I46: 571.73808
A47: Basic EPS, GAAP | B47: IS_EPS | C47: -0.98 | D47: -0.8785 | E47: -1.28 | F47: -0.48 | G47: -0.54 | H47: -0.28 | I47: -0.16 | J47: -0.1 | K47: 0.003
A48: Basic EPS from Cont Ops, GAAP | B48: IS_EARN_BEF_XO_ITEMS_PER_SH | C48: -0.98 | D48: -0.8785 | E48: -1.28 | F48: -0.48 | G48: -0.54 | H48: -0.28 | I48: -0.16 | J48: -0.1 | K48: 0.003
A49: Basic EPS from Cont Ops, Adjusted | B49: IS_BASIC_EPS_CONT_OPS | C49: -0.98 | D49: -0.8562 | E49: -1.2748 | F49: -0.4795 | G49: -0.4276 | H49: -0.2697 | I49: -0.150151 | J49: 0.468 | K49: 0.561
A51: Diluted Weighted Avg Shares | B51: IS_SH_FOR_DILUTED_EPS | C51: 230.4269 | D51: 239.2817 | E51: 277.5435 | F51: 514.2792 | G51: 534.8785 | H51: 556.3174 | I51: 571.73808
A52: Diluted EPS, GAAP | B52: IS_DILUTED_EPS | C52: -0.98 | D52: -0.8785 | E52: -1.28 | F52: -0.48 | G52: -0.54 | H52: -0.28 | I52: -0.16 | J52: -0.1 | K52: 0.003
A53: Diluted EPS from Cont Ops, GAAP | B53: IS_DIL_EPS_BEF_XO | C53: -0.98 | D53: -0.8785 | E53: -1.28 | F53: -0.48 | G53: -0.54 | H53: -0.28 | I53: -0.16 | J53: -0.1 | K53: 0.003
A54: Diluted EPS from Cont Ops, Adjusted | B54: IS_DIL_EPS_CONT_OPS | C54: -0.98 | D54: -0.8562 | E54: -1.2756 | F54: -0.4795 | G54: -0.4316 | H54: -0.2712 | I54: -0.152649 | J54: 0.468 | K54: 0.561
A56: Reference Items
A57: Accounting Standard | B57: ACCOUNTING_STANDARD | C57: US GAAP | D57: US GAAP | E57: US GAAP | F57: US GAAP | G57: US GAAP | H57: US GAAP
A58: EBITDA | B58: EBITDA | C58: -201.35 | D58: -168.361 | E58: -317.97 | F58: -222.091 | G58: -211.471 | H58: -143.575 | I58: -84.633 | J58: 259.33333 | K58: 332.55556
A59: EBITDA Margin (T12M) | B59: EBITDA_MARGIN | C59: -167.9806 | D59: -67.37 | E59: -74.2322 | F59: -34.0346 | G59: -22.5597 | H59: -11.4934 | I59: -5.9323513 | J59: 16.444121 | K59: 17.497127
A60: EBITA | B60: EBITA | C60: -203.602 | D60: -176.284 | E60: -325.026 | F60: -229.958 | G60: -222.21 | H60: -164.224 | I60: -106.735
A61: EBIT | B61: EBIT | C61: -227.818 | D61: -202.711 | E61: -352.316 | F61: -258.399 | G61: -249.92 | H61: -185.095 | I61: -120.778 | J61: 235.882 | K61: 306
A62: Gross Margin | B62: GROSS_MARGIN | C62: 59.6863 | D62: 69.8313 | E62: 70.9384 | F62: 72.0087 | G62: 73.6467 | H62: 76.119 | I62: 76.868575 | J62: 77.468 | K62: 77.349
A63: Operating Margin | B63: OPER_MARGIN | C63: -190.0622 | D63: -81.1152 | E63: -82.2505 | F63: -39.5986 | G63: -26.6614 | H63: -14.8171 | I63: -8.4659356 | J63: 14.95711 | K63: 16.099908
A64: Profit Margin | B64: PROF_MARGIN | C64: -187.8981 | D64: -81.9757 | E64: -82.6002 | F64: -37.7886 | G64: -24.3997 | H64: -12.01 | I64: -5.8745853 | J64: 17.28607 | K64: 17.725104
A65: Dividends per Share | B65: EQY_DPS | C65: 0 | D65: 0 | E65: 0 | F65: 0 | G65: 0 | H65: 0 | I65: 0
A66: Total Cash Common Dividends | B66: IS_TOT_CASH_COM_DVD | C66: 0 | D66: 0 | E66: 0 | F66: 0 | G66: 0 | H66: 0 | I66: 0
A67: Depreciation Expense | B67: IS_DEPR_EXP | C67: 2.252 | D67: 7.923 | E67: 7.056 | F67: 7.867 | G67: 10.739 | H67: 20.649 | I67: 22.102
A68: Rental Expense | B68: BS_CURR_RENTAL_EXPENSE | C68: 23.895 | D68: 25.561 | E68: 24.211 | F68: 25.25 | G68: 24.334 | H68: 21.958 | I68: 15.092
A69: Source: Bloomberg | C69: Right click to show data transparency (not supported for all values)

Sheet Sheet3
A2: Samsara Inc (IOT US) - Standardized
A4: In Millions of USD except Per Share | C4: FY 2020 | D4: FY 2021 | E4: FY 2022 | F4: FY 2023 | G4: FY 2024 | H4: FY 2025
A5: 12 Months Ending | C5: 02/01/2020 | D5: 01/30/2021 | E5: 01/29/2022 | F5: 01/28/2023 | G5: 02/03/2024 | H5: 02/01/2025
A6: Total Assets
A7: + Cash, Cash Equivalents & STI | B7: CASH_CASH_EQTY_STI_DETAILED | C7: 201.069 | D7: 399.887 | E7: 921.218 | F7: 689.862 | G7: 547.662 | H7: 694.798
A8: + Cash & Cash Equivalents | B8: BS_CASH_NEAR_CASH_ITEM | C8: 201.069 | D8: 399.887 | E8: 921.218 | F8: 200.67 | G8: 135.536 | H8: 227.576
A9: + ST Investments | B9: BS_MKT_SEC_OTHER_ST_INVEST | C9: 0 | D9: 0 | E9: 0 | F9: 489.192 | G9: 412.126 | H9: 467.222
A10: + Accounts & Notes Receiv | B10: BS_ACCT_NOTE_RCV | C10: 34.213 | D10: 42.248 | E10: 81.987 | F10: 122.867 | G10: 161.829 | H10: 234.016
A11: + Accounts Receivable, Net | B11: BS_ACCTS_REC_EXCL_NOTES_REC | C11: 34.213 | D11: 42.248 | E11: 81.987 | F11: 122.867 | G11: 161.829 | H11: 234.016
A12: + Notes Receivable, Net | B12: NOTES_RECEIVABLE | C12: — | D12: 0 | E12: 0 | F12: 0 | G12: 0 | H12: 0
A13: + Unbilled Revenues | B13: BS_UNBILLED_REVENUES | C13: 14.736 | D13: 26.059 | E13: 52.519 | F13: 82.046 | G13: — | H13: 119.323
A14: + Inventories | B14: BS_INVENTORIES | C14: 16.516 | D14: 13.674 | E14: 33.067 | F14: 40.571 | G14: 22.238 | H14: 38.911
A15: + Other ST Assets | B15: OTHER_CURRENT_ASSETS_DETAILED | C15: 10.945 | D15: 9.321 | E15: 11.376 | F15: 22.189 | G15: 155.229 | H15: 58.106
A16: + Derivative & Hedging Assets | B16: BS_DERIV_HEDGING_ASST_ST | C16: 0 | D16: 0 | E16: 0 | F16: 0 | G16: 0 | H16: 0
A17: + Misc ST Assets | B17: BS_OTHER_CUR_ASSET_LESS_PREPAY | C17: 10.945 | D17: 9.321 | E17: 11.376 | F17: 22.189 | G17: 155.229 | H17: 58.106
A18: Total Current Assets | B18: BS_CUR_ASSET_REPORT | C18: 277.479 | D18: 491.189 | E18: 1100.167 | F18: 957.535 | G18: 886.958 | H18: 1145.154
A19: + Property, Plant & Equip, Net | B19: BS_NET_FIX_ASSET | C19: 202.227 | D19: 190.776 | E19: 171.199 | F19: 171.902 | G19: 136.943 | H19: 123.015
A20: + Property, Plant & Equip | B20: BS_GROSS_FIX_ASSET | C20: 208.606 | D20: 205.051 | E20: 193.019 | F20: 205.77 | G20: 188.666 | H20: 188.868
A21: - Accumulated Depreciation | B21: BS_ACCUM_DEPR | C21: 6.379 | D21: 14.275 | E21: 21.82 | F21: 33.868 | G21: 51.723 | H21: 65.853
A22: + LT Investments & Receivables | B22: BS_LT_INVEST | C22: 0 | D22: 0 | E22: 0 | F22: 113.101 | G22: 276.166 | H22: 282.652
A23: + LT Investments | B23: BS_LONG_TERM_INVESTMENTS | C23: — | D23: — | E23: — | F23: 113.101 | G23: 276.166 | H23: 282.652
A24: + Other LT Assets | B24: BS_OTHER_ASSETS_DEF_CHRG_OTHER | C24: 151.304 | D24: 204.668 | E24: 296.563 | F24: 374.47 | G24: 434.778 | H24: 473.481
A25: + Total Intangible Assets | B25: BS_DISCLOSED_INTANGIBLES | C25: 0 | D25: 0 | E25: 0 | F25: 0 | G25: 0 | H25: 0
A26: + Goodwill | B26: BS_GOODWILL | C26: 0 | D26: 0 | E26: 0 | F26: 0 | G26: 0 | H26: 0
A27: + Other Intangible Assets | B27: OTHER_INTANGIBLE_ASSETS_DETAILED | C27: 0 | D27: 0 | E27: 0 | F27: 0 | G27: 0 | H27: 0
A28: + Derivative & Hedging Assets | B28: BS_DERIV_HEDGING_ASST_LT | C28: 0 | D28: 0 | E28: 0 | F28: 0 | G28: 0 | H28: 0
A29: + Misc LT Assets | B29: OTHER_NONCURRENT_ASSETS_DETAILED | C29: 151.304 | D29: 204.668 | E29: 296.563 | F29: 374.47 | G29: 434.778 | H29: 473.481
A30: Total Noncurrent Assets | B30: BS_TOT_NON_CUR_ASSET | C30: 353.531 | D30: 395.444 | E30: 467.762 | F30: 659.473 | G30: 847.887 | H30: 879.148
A31: Total Assets | B31: BS_TOT_ASSET | C31: 631.01 | D31: 886.633 | E31: 1567.929 | F31: 1617.008 | G31: 1734.845 | H31: 2024.302
A33: Liabilities & Shareholders' Equity
A34: + Payables & Accruals | B34: ACCT_PAYABLE_ACCRUALS_DETAILED | C34: 36.328 | D34: 46.52 | E34: 113.647 | F34: 119.998 | G34: 144.786 | H34: 182.436
A35: + Accounts Payable | B35: BS_ACCT_PAYABLE | C35: 16.467 | D35: 19.4 | E35: 54.705 | F35: 30.144 | G35: 46.281 | H35: 64.017
A36: + Other Payables & Accruals | B36: BS_ACCRUAL | C36: 19.861 | D36: 27.12 | E36: 58.942 | F36: 89.854 | G36: 98.505 | H36: 118.419
A37: + ST Debt | B37: BS_ST_BORROW | C37: 17.532 | D37: 22.313 | E37: 21.447 | F37: 22.047 | G37: 20.661 | H37: 15.656
A38: + ST Borrowings | B38: SHORT_TERM_DEBT_DETAILED | C38: 0 | D38: 0 | E38: 0 | F38: 0 | G38: 0 | H38: 0
A39: + ST Lease Liabilities | B39: ST_CAPITALIZED_LEASE_LIABILITIES | C39: 17.532 | D39: 22.313 | E39: 21.447 | F39: 22.047 | G39: 20.661 | H39: 15.656
A40: + ST Finance Leases | B40: ST_CAPITAL_LEASE_OBLIGATIONS | C40: 0 | D40: 0 | E40: 0 | F40: 0 | G40: 0 | H40: 0
A41: + ST Operating Leases | B41: BS_ST_OPERATING_LEASE_LIABS | C41: 17.532 | D41: 22.313 | E41: 21.447 | F41: 22.047 | G41: 20.661 | H41: 15.656
A42: + Other ST Liabilities | B42: OTHER_CURRENT_LIABS_SUB_DETAILED | C42: 94.391 | D42: 143.109 | E42: 203.185 | F42: 300.113 | G42: 426.369 | H42: 563.254
A43: + Deferred Revenue | B43: ST_DEFERRED_REVENUE | C43: 94.391 | D43: 143.109 | E43: 203.185 | F43: 300.113 | G43: 426.369 | H43: 563.254
A44: + Derivatives & Hedging | B44: BS_DERIV_HEDGING_LIAB_ST | C44: 0 | D44: 0 | E44: 0 | F44: 0 | G44: 0 | H44: 0
A45: + Misc ST Liabilities | B45: OTHER_CURRENT_LIABS_DETAILED | C45: 0 | D45: 0 | E45: 0 | F45: 0 | G45: 0 | H45: 0
... A53: + Accrued Liabilities | B53: BS_ACCRUED_LIABILITIES | C53: 0 | D53: 0 | E53: 0 | F53: 0 | G53: 0 | H53: 0
A54: + Pension Liabilities | B54: PENSION_LIABILITIES | C54: 0 | D54: 0 | E54: — | F54: — | G54: — | H54: 0
A55: + Pensions | B55: BS_PENSIONS_LT_LIABS | C55: 0 | D55: 0 | E55: — | F55: — | G55: — | H55: 0
A56: + Other Post-Ret Benefits | B56: BS_OPRB_LT_LIABS | C56: 0 | D56: 0 | E56: — | F56: — | G56: — | H56: 0
A57: + Deferred Revenue | B57: LT_DEFERRED_REVENUE | C57: 116.679 | D57: 106.463 | E57: 110.501 | F57: 126.452 | G57: 139.117 | H57: 122.516
A58: + Derivatives & Hedging | B58: BS_DERIV_HEDGING_LIAB_LT | C58: 0 | D58: 0 | E58: 0 | F58: 0 | G58: 0 | H58: 0
A59: + Misc LT Liabilities | B59: OTHER_NONCURRENT_LIABS_DETAILED | C59: 0.644 | D59: 1.003 | E59: 6.689 | F59: 9.506 | G59: 9.935 | H59: 6.622
A60: Total Noncurrent Liabilities | B60: NON_CUR_LIAB | C60: 284.104 | D60: 258.427 | E60: 240.703 | F60: 236.831 | G60: 227.882 | H60: 193.76
A61: Total Liabilities | B61: BS_TOT_LIAB2 | C61: 432.355 | D61: 470.369 | E61: 578.982 | F61: 678.989 | G61: 819.698 | H61: 955.106
A62: + Preferred Equity and Hybrid Capital | B62: PFD_EQTY_HYBRID_CAPITAL | C62: 539.999 | D62: 939.497 | E62: 0 | F62: 0 | G62: 0 | H62: 0
A63: + Share Capital & APIC | B63: BS_SH_CAP_AND_APIC | C63: 4.75 | D63: 42.693 | E63: 1909.993 | F63: 2107.043 | G63: 2368.629 | H63: 2680.047
A64: + Common Stock | B64: BS_COMMON_STOCK | C64: 0.0241 | D64: 0.001 | E64: 0.029 | F64: 0.03 | G64: 0.032 | H64: 0.035
A65: + Additional Paid in Capital | B65: BS_ADD_PAID_IN_CAP | C65: 4.7259 | D65: 42.692 | E65: 1909.964 | F65: 2107.013 | G65: 2368.597 | H65: 2680.012
A66: - Treasury Stock | B66: BS_AMT_OF_TSY_STOCK | C66: 0 | D66: 0 | E66: 0 | F66: 0 | G66: 0 | H66: 0
A67: + Retained Earnings | B67: BS_PURE_RETAINED_EARNINGS | C67: -346.094 | D67: -565.926 | E67: -920.95 | F67: -1168.372 | G67: -1455.098 | H67: -1610.005
A68: + Other Equity | B68: OTHER_EQUITY_RATIO | C68: 0 | D68: 0 | E68: -0.096 | F68: -0.652 | G68: 1.616 | H68: -0.846
... A72: Total Liabilities & Equity | B72: TOT_LIAB_AND_EQY | C72: 631.01 | D72: 886.633 | E72: 1567.929 | F72: 1617.008 | G72: 1734.845 | H72: 2024.302
A74: Reference Items
A75: Accounting Standard | B75: ACCOUNTING_STANDARD | C75: US GAAP | D75: US GAAP | E75: US GAAP | F75: US GAAP | G75: US GAAP | H75: US GAAP
A76: Shares Outstanding | B76: BS_SH_OUT | C76: 241.213 | D76: 245.9855 | E76: 505.4762 | F76: 524.1602 | G76: 545.9735 | H76: 565.7192
A77: Number of Treasury Shares | B77: BS_NUM_OF_TSY_SH | C77: 0 | D77: 0 | E77: 0 | F77: 0 | G77: 0 | H77: 0
A78: Pension Obligations | B78: BS_PENSION_RSRV | C78: 0 | D78: 0 | E78: 0 | F78: 0 | G78: 0 | H78: 0
A79: Future Minimum Operating Lease Obligations | B79: BS_FUTURE_MIN_OPER_LEASE_OBLIG | C79: — | D79: 189.766 | E79: 172.295 | F79: 144.577 | G79: 118.679 | H79: 92.987
A80: Capital Leases - Total | B80: BS_TOTAL_CAPITAL_LEASES | C80: 0 | D80: 0 | E80: 0 | F80: 0 | G80: 0 | H80: 0
A81: Options Granted During Period | B81: BS_OPTIONS_GRANTED | C81: 2.7647 | D81: 3.0513 | E81: — | F81: — | G81: 0 | H81: 0
A82: Options Outstanding at Period End | B82: BS_OPTIONS_OUTSTANDING | C82: 13.9771 | D82: 11.6713 | E82: 8.6281 | F82: 6.9275 | G82: 6.1659 | H82: 5.6325
A83: Net Debt | B83: NET_DEBT | C83: -16.756 | D83: -226.613 | E83: -776.258 | F83: -566.942 | G83: -448.171 | H83: -614.52
A84: Net Debt to Equity | B84: NET_DEBT_TO_SHRHLDR_EQTY | C84: -8.4347 | D84: -54.4397 | E84: -78.4934 | F84: -60.4404 | G84: -48.9726 | H84: -57.475
A85: Tangible Common Equity Ratio | B85: TCE_RATIO | C85: -54.0949 | D85: -59.0135 | E85: 63.0735 | F85: 58.0095 | G85: 52.7509 | H85: 52.818
A86: Current Ratio | B86: CUR_RATIO | C86: 1.8717 | D86: 2.3176 | E86: 3.2522 | F86: 2.1656 | G86: 1.4987 | H86: 1.5041
A87: Cash Conversion Cycle | B87: CASH_CONVERSION_CYCLE | C87: — | D87: 38.5887 | E87: 27.3828 | F87: 49.3009 | G87: 41.5139 | H87: 31.2489
A88: Source: Bloomberg | C88: Right click to show data transparency (not supported for all values)

Sheet Sheet4
A2: Samsara Inc (IOT US) - Standardized
A4: In Millions of USD except Per Share | C4: FY 2020 | D4: FY 2021 | E4: FY 2022 | F4: FY 2023 | G4: FY 2024 | H4: FY 2025 | I4: Last 12M
A5: 12 Months Ending | C5: 02/01/2020 | D5: 01/30/2021 | E5: 01/29/2022 | F5: 01/28/2023 | G5: 02/03/2024 | H5: 02/01/2025 | I5: 08/02/2025
A6: Cash from Operating Activities
A7: + Net Income | B7: CF_NET_INC | C7: -225.224 | D7: -210.208 | E7: -355.024 | F7: -247.422 | G7: -286.726 | H7: -154.907 | I7: -87.929
A8: + Depreciation & Amortization | B8: CF_DEPR_AMORT | C8: 4.32 | D8: 10.738 | E8: 10.388 | F8: 11.768 | G8: 15.526 | H8: 20.649 | I8: 22.102
A9: + Non-Cash Items | B9: NON_CASH_ITEMS_DETAILED | C9: -19.654 | D9: -14.036 | E9: 193.389 | F9: 155.616 | G9: 208.926 | H9: 240.643 | I9: 257.632
A10: + Stock-Based Compensation | B10: CF_STOCK_BASED_COMPENSATION | C10: 2.868 | D10: 25.564 | E10: 228.723 | F10: 177.473 | G10: 237.082 | H10: 277.87 | I10: 299.824
A11: + Other Non-Cash Adj | B11: OTHER_NON_CASH_ADJ_LESS_DETAILED | C11: -22.522 | D11: -39.6 | E11: -35.334 | F11: -21.857 | G11: -28.156 | H11: -37.227 | I11: -42.192
A12: + Chg in Non-Cash Work Cap | B12: CF_CHNG_NON_CASH_WORK_CAP | C12: 48.033 | D12: 41.737 | E12: -20.234 | F12: -22.983 | G12: 50.459 | H12: 25.274 | I12: 0.84
A13: + (Inc) Dec in Accts Receiv | B13: CF_ACCT_RCV_UNBILLED_REV | C13: -10.911 | D13: -14.14 | E13: -47.049 | F13: -47.464 | G13: -46.42 | H13: -75.531 | I13: -69.471
A14: + (Inc) Dec in Inventories | B14: CF_CHANGE_IN_INVENTORIES | C14: -7.62 | D14: 2.843 | E14: -19.393 | F14: -7.504 | G14: 18.332 | H14: -22.416 | I14: -17.953
A15: + Inc (Dec) in Other | B15: INC_DEC_IN_OT_OP_AST_LIAB_DETAIL | C15: 66.564 | D15: 53.034 | E15: 46.208 | F15: 31.985 | G15: 78.547 | H15: 123.221 | I15: 88.264
A16: + Net Cash From Disc Ops | B16: CF_NET_CASH_DISCONT_OPS_OPER | C16: 0 | D16: 0 | E16: 0 | F16: 0 | G16: 0 | H16: 0 | I16: 0
A17: Cash from Operating Activities | B17: CF_CASH_FROM_OPER | C17: -192.525 | D17: -171.769 | E17: -171.481 | F17: -103.021 | G17: -11.815 | H17: 131.659 | I17: 192.645
A19: Cash from Investing Activities
A20: + Change in Fixed & Intang | B20: FIXED_INTANG_ASST_CHANGE | C20: -29.99 | D20: -32.102 | E20: -19.353 | F20: -33.24 | G20: -10.953 | H20: -20.177 | I20: -23.012
A21: + Disp in Fixed & Intang | B21: DISPOSAL_OF_FIXED_INTANG | C21: 0 | D21: 0 | E21: 0 | F21: 0 | G21: 0 | H21: 0 | I21: 0
A22: + Disp of Fixed Prod Assets | B22: CF_DISPOSAL_OF_FIXED_PROD_ASSETS | C22: 0 | D22: 0 | E22: — | F22: 0 | G22: 0 | H22: 0 | I22: 0
A23: + Disp of Intangible Assets | B23: CF_DISPOSAL_OF_INTANGIBLE_ASSETS | C23: 0 | D23: 0 | E23: — | F23: 0 | G23: 0 | H23: 0 | I23: 0
A24: + Acq of Fixed & Intang | B24: ACQUIS_OF_FIXED_INTANG | C24: -29.99 | D24: -32.102 | E24: -19.353 | F24: -33.24 | G24: -10.953 | H24: -20.177 | I24: -23.012
A25: + Acq of Fixed Prod Assets | B25: CF_PURCHASE_OF_FIXED_PROD_ASSETS | C25: -29.99 | D25: -32.102 | E25: -19.353 | F25: -33.24 | G25: -10.953 | H25: -20.177 | I25: -23.012
A26: + Acq of Intangible Assets | B26: CF_ACQUISITION_OF_INTANG_ASSETS | C26: 0 | D26: 0 | E26: 0 | F26: 0 | G26: 0 | H26: 0 | I26: 0
A27: + Net Change in LT Investment | B27: NET_CHG_IN_LT_INVEST_DETAILED | C27: 0 | D27: 0 | E27: 0 | F27: 0 | G27: 0 | H27: 0 | I27: 0
A28: + Dec in LT Investment | B28: CF_DECR_INVEST | C28: 0 | D28: 0 | E28: 0 | F28: 0 | G28: 0 | H28: 0 | I28: 0
A29: + Inc in LT Investment | B29: CF_INCR_INVEST | C29: 0 | D29: 0 | E29: 0 | F29: 0 | G29: 0 | H29: 0 | I29: 0
A30: + Net Cash From Acq & Div | B30: CF_NT_CSH_RCVD_PD_FOR_ACQUIS_DIV | C30: 0 | D30: 0 | E30: 0 | F30: 0 | G30: 0 | H30: 0 | I30: 0
A31: + Cash from Divestitures | B31: CF_CASH_FOR_DIVESTITURES | C31: 0 | D31: 0 | E31: 0 | F31: 0 | G31: 0 | H31: 0 | I31: 0
A32: + Cash for Acq of Subs | B32: CF_CASH_FOR_ACQUIS_SUBSIDIARIES | C32: 0 | D32: 0 | E32: 0 | F32: 0 | G32: 0 | H32: 0 | I32: 0
A33: + Cash for JVs | B33: CF_CASH_FOR_JOINT_VENTURES_ASSOC | C33: 0 | D33: 0 | E33: 0 | F33: 0 | G33: 0 | H33: 0 | I33: 0
A34: + Other Investing Activities | B34: OTHER_INVESTING_ACT_DETAILED | C34: 0 | D34: -0.1 | E34: -0.682 | F34: -598.608 | G34: -67.734 | H34: -46.444 | I34: -96.816
A35: + Net Cash From Disc Ops | B35: CF_NET_CASH_DISCONTINUED_OPS_INV | C35: 0 | D35: 0 | E35: 0 | F35: 0 | G35: 0 | H35: 0 | I35: 0
A36: Cash from Investing Activities | B36: CF_CASH_FROM_INV_ACT | C36: -29.99 | D36: -32.202 | E36: -20.035 | F36: -631.848 | G36: -78.687 | H36: -66.621 | I36: -119.828
A38: Cash from Financing Activities
A39: + Dividends Paid | B39: CF_DVD_PAID | C39: 0 | D39: 0 | E39: 0 | F39: 0 | G39: 0 | H39: 0 | I39: 0
A40: + Cash From (Repayment) Debt | B40: PROC_FR_REPAYMNTS_BOR_DETAILED | C40: 0 | D40: -0.168 | E40: -0.545 | F40: -1.303 | G40: -2.205 | H40: -1.691 | I40: -1.441
A41: + Cash From (Repay) ST Debt | B41: CF_NET_CHG_ST_DEBT_CPTL_LEAS | C41: 0 | D41: 0 | E41: — | F41: 0 | G41: 0 | H41: 0 | I41: 0
A42: + Cash From LT Debt | B42: CF_LT_DEBT_CAP_LEAS_PROCEEDS | C42: 0 | D42: 0 | E42: — | F42: 0 | G42: 0 | H42: 0 | I42: 0
A43: + Repayments of LT Debt | B43: CF_LT_DEBT_CAP_LEAS_PAYMENT | C43: 0 | D43: -0.168 | E43: -0.545 | F43: -1.303 | G43: -2.205 | H43: -1.691 | I43: -1.441
A44: + Cash (Repurchase) of Equity | B44: PROC_FR_REPURCH_EQTY_DETAILED | C44: 300.855 | D44: 402.142 | E44: 706.294 | F44: 18.047 | G44: 23.202 | H44: 28.799 | I44: 30.613
A45: + Increase in Capital Stock | B45: CF_INCR_CAP_STOCK | C45: 300.885 | D45: 402.203 | E45: 706.299 | F45: 18.047 | G45: 23.202 | H45: 28.799 | I45: 30.613
A46: + Decrease in Capital Stock | B46: CF_DECR_CAP_STOCK | C46: -0.03 | D46: -0.061 | E46: -0.005 | F46: 0 | G46: 0 | H46: 0 | I46: 0
A47: + Other Financing Activities | B47: OTHER_FIN_AND_DEC_CAP | C47: -5.002 | D47: 0 | E47: -4.105 | F47: -2.532 | G47: 0 | H47: -0.007 | I47: -0.007
A48: + Net Cash From Disc Ops | B48: CF_NET_CASH_DISCONTINUED_OPS_FIN | C48: 0 | D48: 0 | E48: 0 | F48: 0 | G48: 0 | H48: 0 | I48: 0
A49: Cash from Financing Activities | B49: CFF_ACTIVITIES_DETAILED | C49: 295.853 | D49: 401.974 | E49: 701.644 | F49: 14.212 | G49: 20.997 | H49: 27.101 | I49: 29.165
A51: Effect of Foreign Exchange Rates | B51: CF_EFFECT_FOREIGN_EXCHANGES | C51: 0 | D51: 0 | E51: -0.127 | F51: 0.113 | G51: 0.477 | H51: -1.083 | I51: 0.824
A53: Net Changes in Cash | B53: CF_NET_CHNG_CASH | C53: 73.338 | D53: 198.003 | E53: 510.001 | F53: -720.544 | G53: -69.028 | H53: 91.056 | I53: 102.806
A55: Cash Paid for Taxes | B55: CF_CASH_PAID_FOR_TAX | C55: 0.001 | D55: 0.031 | E55: 0.467 | F55: 0.607 | G55: 2.122 | H55: 3.463 | I55: 4.145
A57: Reference Items
A58: EBITDA | B58: EBITDA | C58: -201.35 | D58: -175.129 | E58: -319.502 | F58: -223.147 | G58: -284.898 | H58: -148.453 | I58: -89.511
A59: Trailing 12M EBITDA Margin | B59: EBITDA_MARGIN | C59: -167.9806 | D59: -70.0782 | E59: -74.5899 | F59: -34.1964 | G59: -30.3928 | H59: -11.8839 | I59: -6.2742748
A60: Free Cash Flow | B60: CF_FREE_CASH_FLOW | C60: -222.515 | D60: -203.871 | E60: -190.834 | F60: -136.261 | G60: -22.768 | H60: 111.482 | I60: 169.633
A61: Free Cash Flow to Equity | B61: FREE_CASH_FLOW_EQUITY | C61: — | D61: 195.459 | E61: -1130.876 | F61: -137.564 | G61: -24.973 | H61: 109.791 | I61: 168.192
A62: Free Cash Flow per Basic Share | B62: FREE_CASH_FLOW_PER_SH | C62: -0.9657 | D62: -0.852 | E62: -0.6876 | F62: -0.265 | G62: -0.0426 | H62: 0.2004 | I62: 0.29971505
A63: Price to Free Cash Flow | B63: PX_TO_FREE_CASH_FLOW | C63: — | D63: — | E63: — | F63: — | G63: — | H63: 256.9953 | I63: 129.28947
A64: Source: Bloomberg | C64: Right click to show data transparency (not supported for all values)

Sheet Sheet2
A1: Samsara Inc- Company Financial (Multiple Periods)
A2: IOT US Equity Periodicity:A Currency:USD Estimate Source:BST Actual Source:Bloomberg
A3: In Millions of USD | D3: 2018 A (Rep) | E3: 2019 A (Rep) | F3: 2020 A (Rep) | G3: 2021 A (Rep) | H3: 2022 A (Rep) | I3: 2023 A (Rep) | J3: 2024 A (Rep) | K3: 2025 A (Rep) | L3: 2026 A (Fwd) | M3: 2027 A (Fwd)
A4: 12 Months Ending | B4: Field Expression | C4: Segment Id | D4: 43130 | E4: 43495 | F4: 43862 | G4: 44226 | H4: 44590 | I4: 44954 | J4: 45325 | K4: 45689 | L4: 46053 | M4: 46417
B8: Income Statement (Adjusted)
B9: Revenue | C9: IS902 | F9: 119.865 | G9: 249.905 | H9: 428.345 | I9: 652.545 | J9: 937.4 | K9: 1249.199 | L9: 1577.0556 | M9: 1900.6316
B11: Cost of Revenue | C11: IM057 | J11: 247.032 | K11: 282.972 | L11: 355.09879 | M11: 429.47397
B12: Gross Profit | C12: IS923 | F12: 71.549 | G12: 174.525 | H12: 310.205 | I12: 479.355 | J12: 703.078 | K12: 966.227 | L12: 1221.2847 | M12: 1467.7794
B13: Gross Margin (%) | C13: IM092 | H13: 72 | I13: 73 | J13: 75 | K13: 77 | L13: 77.468031 | M13: 77.348724
B15: Total Operating Expenses | C15: IM744 | L15: 985.66495 | M15: 1164.8521
B16: Research & Development Expense | C16: IS925 | F16: 66.812 | G16: 85.955 | H16: 102.276 | I16: 187.405 | J16: 163.361 | K16: 192.466 | L16: 220.73672 | M16: 263.18028
B17: Selling, & Marketing Expense | C17: IM059 | F17: 179.393 | G17: 195.315 | H17: 228.661 | I17: 316.026 | J17: 411.446 | K17: 511.177 | L17: 589.63636 | M17: 699.57561
B18: General & Administrative | C18: IM060 | F18: 44.953 | G18: 70.402 | H18: 93.346 | I18: 117.083 | J18: 127.001 | K18: 149.032 | L18: 175.14895 | M18: 201.27737
B19: Depreciation Expense | C19: F1702 | F19: 2.252 | G19: 7.923 | H19: 7.056 | I19: 7.867 | J19: 10.739 | K19: 20.649 | L19: 23.047271 | M19: 27.750107
B21: Operating Income | C21: IM132 | H21: -114.078 | I21: -76.975 | J21: 1.27 | K21: 113.552 | L21: 235.88235 | M21: 306
B22: Operating Margin (%) | C22: RX609 | F22: -183.21362 | G22: -70.885737 | H22: -26.542623 | I22: -11.796121 | J22: 0.13548329 | K22: 9.0899849 | L22: 14.941852 | M22: 15.962708
B24: EBITDA | C24: IM131 | H24: -103.69 | I24: -65.207 | J24: 16.796 | K24: 118.356 | L24: 259.33333 | M24: 332.55556
B26: Non-Operating Income | C26: IS037 | F26: -2.934 | G26: 0.642 | H26: 0.002 | I26: -15.62 | J26: -39.964 | K26: -39.559 | L26: -45.256057 | M26: -44.783984
B27: Pre-Tax Income | C27: IS924 | F27: -216.675 | G27: -177.789 | H27: -114.08 | I27: -61.355 | J27: 41.234 | K27: 153.111 | L27: 280.50947 | M27: 346.57933
B28: As % of Revenue | C28: IL455 | F28: 0.34 | G28: 0.087 | H28: 1.174 | I28: 3.587 | J28: 3.343 | K28: 4.493 | L28: 6.5235375 | M28: 10.924399
B30: Income Tax Expense | C30: IS038 | F30: 0.34 | G30: 0.087 | H30: 1.174 | I30: 3.587 | J30: 3.343 | K30: 4.493 | L30: 8.4538672 | M30: 18.216614
B32: Income from Continue Operations | C32: IS040 | F32: -225.224 | G32: -210.208 | H32: -355.024 | I32: -247.422 | J32: -286.726 | K32: -154.907 | L32: -64.734825 | M32: -0.92458726
B33: Net Income Available to Common | C33: IS903 | H33: -355.024 | I33: -64.942 | J33: 37.891 | K33: 148.618 | L33: 272.61111 | M33: 336.88889
B35: Basic Weighted Avg. Shares | C35: IS060 | F35: 230.4269 | G35: 239.2817 | H35: 277.54347 | I35: 514.27923 | J35: 534.8785 | K35: 556.31744 | L35: 574.91847 | M35: 585.73496
B37: Diluted Weighted Avg. Shares | C37: IS062 | F37: 230.4269 | G37: 239.2817 | H37: 277.54347 | I37: 514.27923 | J37: 534.8785 | K37: 556.31744 | L37: 583.84368 | M37: 593.57416
B38: Diluted EPS | C38: IS900 | H38: -0.42 | I38: -0.13 | J38: 0.07 | K38: 0.26 | L38: 0.46777778 | M38: 0.56105263

Sheet IS
A1: Samsara, Inc. Class A (IOT)
A2: $38.72
A5: Samsara, Inc. Class A
A6: IOT 79589L106 BPK3058 NYSE Common stock
A7: Source: FactSet Fundamentals
B8: JAN '20 | C8: JAN '21 | D8: JAN '22 | E8: JAN '23 | F8: JAN '24 | G8: JAN '25 | H8: JUL '25
H9: LTM
A10: Sales | B10: 119.865 | C10: 249.905 | D10: 428.345 | E10: 652.545 | F10: 937.385 | G10: 1249.199 | H10: 1426.635
A11: Cost of Goods Sold (COGS) incl. D&A | B11: 48.322 | C11: 75.393 | D11: 124.484 | E11: 182.656 | F11: 247.032 | G11: 298.321 | H11: 330.001
A12: COGS excluding D&A | B12: 23.517 | C12: 38.281 | D12: 75.02 | E12: 105.918 | F12: 134.727 | G12: 160.86 | H12: 180.846
A13: Depreciation & Amortization Expense | B13: 24.805 | C13: 37.112 | D13: 49.464 | E13: 76.738 | F13: 112.305 | G13: 137.461 | H13: 149.155
A14: Depreciation | B14: 15.705 | C14: 17.112 | D14: 9.564 | E14: 11.768 | F14: 15.526 | G14: 20.649 | H14: 22.102
A15: Amortization of Deferred Charges | B15: 9.1 | C15: 20 | D15: 39.9 | E15: 64.97 | F15: 96.779 | G15: 116.812 | H15: 127.053
A16: Gross Income | B16: 71.543 | C16: 174.512 | D16: 303.861 | E16: 469.889 | F16: 690.353 | G16: 950.878 | H16: 1096.634
A17: SG&A Expense | B17: 299.361 | C17: 377.223 | D17: 656.177 | E17: 728.288 | F17: 940.273 | G17: 1135.973 | H17: 1217.412
A18: Research & Development | B18: 70.466 | C18: 99.738 | D18: 205.125 | E18: 187.405 | F18: 258.581 | G18: 299.716 | H18: 319.121
A19: Other SG&A | B19: 228.895 | C19: 277.485 | D19: 451.052 | E19: 540.883 | F19: 681.692 | G19: 836.257 | H19: 898.291
A20: EBIT (Operating Income) | B20: -227.818 | C20: -202.711 | D20: -352.316 | E20: -258.399 | F20: -249.92 | G20: -185.095 | H20: -120.778
A21: Nonoperating Income - Net | B21: 2.934 | C21: -0.642 | D21: -0.002 | E21: 15.62 | F21: 39.964 | G21: 39.559 | H21: 43.998
... A23: Unusual Expense - Net | B23: 0 | C23: 6.768 | D23: 1.532 | E23: 1.056 | F23: 73.427 | G23: 4.878 | H23: 4.878
A24: Impairments | C24: 0 | D24: 1.532 | E24: 1.056 | F24: 4.762 | G24: 4.028
A25: Property,Plant & Equipment | C25: 0 | D25: 1.532 | E25: 1.056 | F25: 4.762 | G25: 4.028
A26: Restructuring Expense | B26: 0 | C26: 6.768 | D26: 0 | E26: 0 | F26: 0 | G26: 0 | H26: 0
A27: Legal Claim Expense | F27: 68.665 | G27: 0.85
A28: Pretax Income | B28: -224.884 | C28: -210.121 | D28: -353.85 | E28: -243.835 | F28: -283.383 | G28: -150.414 | H28: -81.658
A29: Income Taxes | B29: 0.34 | C29: 0.087 | D29: 1.174 | E29: 3.587 | F29: 3.343 | G29: 4.493 | H29: 6.271
A30: Income Taxes - Current Domestic | B30: 0.001 | C30: 0.112 | D30: 0.053 | E30: 0.585 | F30: 0.494 | G30: 0.201
A31: Income Taxes - Current Foreign | B31: 0.339 | C31: 0.275 | D31: 0.082 | E31: 1.007 | F31: 1.918 | G31: 2.219
A32: Income Taxes - Deferred Foreign | B32: 0 | C32: -0.3 | D32: 1.039 | E32: 1.995 | F32: 0.931 | G32: 2.073
A33: Consolidated Net Income | B33: -225.224 | C33: -210.208 | D33: -355.024 | E33: -247.422 | F33: -286.726 | G33: -154.907 | H33: -87.929
A34: Net Income | B34: -225.224 | C34: -210.208 | D34: -355.024 | E34: -247.422 | F34: -286.726 | G34: -154.907 | H34: -87.929
A35: Preferred Dividends | B35: 0 | C35: 9.624 | D35: 0 | E35: 0 | F35: 0 | G35: 0 | H35: 0
A36: Net Income available to Common | B36: -225.224 | C36: -219.832 | D36: -355.024 | E36: -247.422 | F36: -286.726 | G36: -154.907 | H36: -87.929
A37: Per Share
A38: EPS (recurring) | B38: -0.450114 | C38: -0.42987 | D38: -0.700234 | E38: -0.479667 | F38: -0.439964 | G38: -0.272313 | H38: -0.14782
A39: EPS (basic) | B39: -0.4501 | C39: -0.4393 | D39: -0.7024 | E39: -0.4811 | F39: -0.5361 | G39: -0.2784 | H39: -0.1558
A40: Basic Shares Outstanding | B40: 500.37126 | C40: 500.37126 | D40: 505.47616 | E40: 514.27923 | F40: 534.8785 | G40: 556.31744 | H40: 571.73808
A41: Total Shares Outstanding | B41: 500.37126 | C41: 500.37126 | D41: 505.47616 | E41: 524.16021 | F41: 545.97353 | G41: 565.71924 | H41: 573.63464
A42: EPS (diluted) | B42: -0.4501 | C42: -0.4393 | D42: -0.7024 | E42: -0.4811 | F42: -0.5361 | G42: -0.2784 | H42: -0.1558
A43: Diluted Shares Outstanding | B43: 500.37126 | C43: 500.37126 | D43: 505.47616 | E43: 514.27923 | F43: 534.8785 | G43: 556.31744 | H43: 571.73808
A44: Total Shares Outstanding | B44: 500.37126 | C44: 500.37126 | D44: 505.47616 | E44: 524.16021 | F44: 545.97353 | G44: 565.71924 | H44: 573.63464
A45: Earnings Persistence | C45: 90.305 | D45: 66.024 | E45: 47.542 | F45: 70.536 | G45: 74.944
A46: EBITDA
A47: EBITDA | B47: -203.013 | C47: -165.599 | D47: -302.852 | E47: -181.661 | F47: -137.615 | G47: -47.634 | H47: 28.377
A48: EBIT | B48: -227.818 | C48: -202.711 | D48: -352.316 | E48: -258.399 | F48: -249.92 | G48: -185.095 | H48: -120.778
A49: Depreciation & Amortization Expense | B49: 24.805 | C49: 37.112 | D49: 49.464 | E49: 76.738 | F49: 112.305 | G49: 137.461 | H49: 149.155
A50: All figures in millions of U.S. Dollar except per share items.

Sheet BS
A1: Samsara, Inc. Class A (IOT)
A2: $38.72
A5: Samsara, Inc. Class A
A6: IOT 79589L106 BPK3058 NYSE Common stock
A7: Source: FactSet Fundamentals
B8: JAN '20 | C8: JAN '21 | D8: JAN '22 | E8: JAN '23 | F8: JAN '24 | G8: JAN '25
A9: Assets
A10: Cash & Short-Term Investments | B10: 201.069 | C10: 399.887 | D10: 921.218 | E10: 689.862 | F10: 547.662 | G10: 694.798
A11: Cash Only | B11: 201.069 | C11: 399.887 | D11: 921.218 | E11: 200.67 | F11: 135.536 | G11: 227.576
A12: Total Short Term Investments | B12: 0 | C12: 0 | D12: 0 | E12: 489.192 | F12: 412.126 | G12: 467.222
A13: Short-Term Receivables | B13: 34.213 | C13: 42.248 | D13: 81.987 | E13: 124.867 | F13: 166.729 | G13: 240.216
A14: Accounts Receivables, Net | B14: 34.213 | C14: 42.248 | D14: 81.987 | E14: 122.867 | F14: 161.829 | G14: 234.016
A15: Accounts Receivables, Gross | B15: 34.413 | C15: 45.448 | D15: 86.387 | E15: 122.867 | F15: 169.629 | G15: 243.116
A16: Bad Debt/Doubtful Accounts | B16: -0.2 | C16: -3.2 | D16: -4.4 | F16: -7.8 | G16: -9.1
A17: Other Receivables | B17: 0 | C17: 0 | D17: 0 | E17: 2 | F17: 4.9 | G17: 6.2
A18: Inventories | B18: 16.516 | C18: 13.674 | D18: 33.067 | E18: 40.571 | F18: 22.238 | G18: 38.911
A19: Finished Goods | B19: 16.516 | C19: 13.674 | D19: 33.067 | E19: 40.571 | F19: 22.238 | G19: 30.459
A20: Raw Materials | B20: 0 | C20: 0 | D20: 0 | E20: 0 | F20: 0 | G20: 8.452
A21: Other Current Assets | B21: 10.945 | C21: 9.321 | D21: 11.376 | E21: 20.189 | F21: 46.321 | G21: 51.906
A22: Miscellaneous Current Assets | B22: 10.945 | C22: 9.321 | D22: 11.376 | E22: 20.189 | F22: 46.321 | G22: 51.906
A23: Total Current Assets | B23: 262.743 | C23: 465.13 | D23: 1047.648 | E23: 875.489 | F23: 782.95 | G23: 1025.831
A24: Net Property, Plant & Equipment | B24: 202.227 | C24: 190.776 | D24: 171.199 | E24: 171.902 | F24: 136.943 | G24: 123.015
A25: Property, Plant & Equipment - Gross | B25: 208.606 | C25: 205.051 | D25: 193.019 | E25: 205.77 | F25: 188.666 | G25: 188.868
A26: Computer Software and Equipment | B26: 0.13 | C26: 0.508 | D26: 0.834 | E26: 1.257 | F26: 1.758 | G26: 6.579
A27: Other Property, Plant & Equipment | B27: 48.926 | C27: 71.422 | D27: 57.758 | E27: 91.889 | F27: 104.934 | G27: 117.425
A28: Operating Lease Right-of-Use Assets | B28: 159.55 | C28: 133.121 | D28: 134.427 | E28: 112.624 | F28: 81.974 | G28: 64.864
... A35: Total Assets | B35: 631.01 | C35: 886.633 | D35: 1567.929 | E35: 1617.008 | F35: 1734.845 | G35: 2024.302
A36: Liabilities & Shareholders' Equity
A37: Current
A38: ST Debt & Curr. Portion LT Debt | B38: 17.532 | C38: 22.313 | D38: 21.447 | E38: 22.047 | F38: 20.661 | G38: 15.656
A39: Accounts Payable | B39: 16.467 | C39: 19.4 | D39: 54.705 | E39: 30.144 | F39: 46.281 | G39: 64.017
A40: Other Current Liabilities | B40: 114.252 | C40: 170.229 | D40: 262.127 | E40: 389.967 | F40: 524.874 | G40: 681.673
A41: Accrued Payroll | B41: 11.9 | C41: 12.549 | D41: 27.107 | E41: 36.03 | F41: 37.068 | G41: 43.443
A42: Miscellaneous Current Liabilities | B42: 102.352 | C42: 157.68 | D42: 235.02 | E42: 353.937 | F42: 487.806 | G42: 638.23
A43: Total Current Liabilities | B43: 148.251 | C43: 211.942 | D43: 338.279 | E43: 442.158 | F43: 591.816 | G43: 761.346
A44: Long-Term
A45: Long-Term Debt | B45: 706.398 | C45: 1100.028 | D45: 123.513 | E45: 100.873 | F45: 78.83 | G45: 64.622
A46: Long-Term Debt excl Lease Obligations | B46: 539.617 | C46: 949.067 | D46: 0 | E46: 0 | F46: 0 | G46: 0
A47: Capital and Operating Lease Obligations | B47: 166.781 | C47: 150.961 | D47: 123.513 | E47: 100.873 | F47: 78.83 | G47: 64.622
A48: Other Liabilities | B48: 117.323 | C48: 107.466 | D48: 117.19 | E48: 135.958 | F48: 149.052 | G48: 129.138
A49: Other Liabilities (excl. Deferred Income) | B49: 0.644 | C49: 1.003 | D49: 6.689 | E49: 9.506 | F49: 9.935 | G49: 6.622
A50: Deferred Income | B50: 116.679 | C50: 106.463 | D50: 110.501 | E50: 126.452 | F50: 139.117 | G50: 122.516
A51: Total Liabilities | B51: 971.972 | C51: 1419.436 | D51: 578.982 | E51: 678.989 | F51: 819.698 | G51: 955.106
A52: Equity
A53: Common Equity | B53: -340.962 | C53: -532.803 | D53: 988.947 | E53: 938.019 | F53: 915.147 | G53: 1069.196
A54: Common Stock Par/Carry Value | B54: 0 | C54: 0.001 | D54: 0.029 | E54: 0.03 | F54: 0.032 | G54: 0.035
A55: Additional Paid-In Capital/Capital Surplus | B55: 5.132 | C55: 33.122 | D55: 1909.964 | E55: 2107.013 | F55: 2368.597 | G55: 2680.012
A56: Retained Earnings | B56: -346.094 | C56: -565.926 | D56: -920.95 | E56: -1168.372 | F56: -1455.098 | G56: -1610.005
A57: Cumulative Translation Adjustment/Unrealized For. Exch. Gain | B57: 0 | C57: 0 | D57: -0.096
A58: Other Appropriated Reserves | E58: -0.652 | F58: 1.616 | G58: -0.846
A59: Total Shareholders' Equity | B59: -340.962 | C59: -532.803 | D59: 988.947 | E59: 938.019 | F59: 915.147 | G59: 1069.196
A60: Total Equity | B60: -340.962 | C60: -532.803 | D60: 988.947 | E60: 938.019 | F60: 915.147 | G60: 1069.196
A61: Total Liabilities & Shareholders' Equity | B61: 631.01 | C61: 886.633 | D61: 1567.929 | E61: 1617.008 | F61: 1734.845 | G61: 2024.302
A62: Per Share
A63: Book Value per Share | B63: -0.68142 | C63: -1.06482 | D63: 1.95647 | E63: 1.78957 | F63: 1.67617 | G63: 1.88998
A64: Tangible Book Value per Share | B64: -0.681418 | C64: -1.064815 | D64: 1.956466 | E64: 1.789565 | F64: 1.676175 | G64: 1.889976
A65: All figures in millions of U.S. Dollar except per share items.

Sheet CFS
A1: Samsara, Inc. Class A (IOT)
A2: $38.72
A5: Samsara, Inc. Class A
A6: IOT 79589L106 BPK3058 NYSE Common stock
A7: Source: FactSet Fundamentals
B8: JAN '20 | C8: JAN '21 | D8: JAN '22 | E8: JAN '23 | F8: JAN '24 | G8: JAN '25 | H8: JUL '25
H9: LTM
A10: GAAP/IFRS Cash Flow
A11: Operating Activities
A12: Net Income / Starting Line | B12: -225.224 | C12: -200.584 | D12: -355.024 | E12: -247.422 | F12: -286.726 | G12: -154.907 | H12: -87.929
A13: Depreciation, Depletion & Amortization | B13: 15.705 | C13: 17.112 | D13: 9.564 | E13: 11.768 | F13: 15.526 | G13: 20.649 | H13: 22.102
A14: Depreciation and Depletion | B14: 15.705 | C14: 17.112 | D14: 9.564 | E14: 11.768 | F14: 15.526 | G14: 20.649 | H14: 22.102
A15: Other Funds | B15: 3.095 | C15: 26.352 | D15: 237.709 | E15: 180.649 | F15: 238.193 | G15: 267.87 | H15: 290.37
A16: Funds from Operations | B16: -206.424 | C16: -157.12 | D16: -107.751 | E16: -55.005 | F16: -33.007 | G16: 133.612 | H16: 224.543
A17: Changes in Working Capital | B17: 13.899 | C17: -14.649 | D17: -63.73 | E17: -48.016 | F17: 21.192 | G17: -1.953 | H17: -31.898
A18: Receivables | B18: -10.911 | C18: -14.14 | D18: -47.049 | E18: -47.464 | F18: -46.42 | G18: -75.531 | H18: -69.471
A19: Inventories | B19: -7.62 | C19: 2.843 | D19: -19.393 | E19: -7.504 | F19: 18.332 | G19: -22.416 | H19: -17.953
A20: Accounts Payable | B20: 11.56 | C20: 16.25 | D20: 69.926 | E20: 13.485 | F20: 26.596 | G20: 37.283 | H20: 24.028
A21: Other Assets/Liabilities | B21: 20.87 | C21: -19.602 | D21: -67.214 | E21: -6.533 | F21: 22.684 | G21: 58.711 | H21: 31.498
A22: Net Operating Cash Flow | B22: -192.525 | C22: -171.769 | D22: -171.481 | E22: -103.021 | F22: -11.815 | G22: 131.659 | H22: 192.645
A23: Investing Activities
A24: Capital Expenditures | B24: -29.99 | C24: -32.102 | D24: -19.353 | E24: -33.24 | F24: -10.953 | G24: -20.177 | H24: -23.012
A25: Capital Expenditures (Fixed Assets) | B25: -29.99 | C25: -32.102 | D25: -19.353 | E25: -33.24 | F25: -10.953 | G25: -20.177 | H25: -23.012
A26: Purchase/Sale of Investments | B26: 0 | C26: 0 | D26: 0 | E26: -598.99 | F26: -67.684 | G26: -46.244 | H26: -96.516
A27: Purchase of Investments | B27: 0 | C27: 0 | D27: 0 | E27: 685.615 | F27: 740.546 | G27: 649.478 | H27: 741.367
A28: Sale/Maturity of Investments | B28: 0 | C28: 0 | D28: 0 | E28: 86.625 | F28: 672.862 | G28: 603.234 | H28: 644.851
A29: Other Funds | B29: 0 | C29: -0.1 | D29: -0.682 | E29: 0.382 | F29: -0.05 | G29: -0.2 | H29: -0.3
A30: Other Uses | B30: 0 | C30: -0.1 | D30: -0.682 | E30: 0 | F30: -0.05 | G30: -0.2 | H30: -0.3
A31: Other Sources | B31: 0 | C31: 0 | D31: 0 | E31: 0.382 | F31: 0 | G31: 0 | H31: 0
A32: Net Investing Cash Flow | B32: -29.99 | C32: -32.202 | D32: -20.035 | E32: -631.848 | F32: -78.687 | G32: -66.621 | H32: -119.828
A33: Financing Activities
A34: Change in Capital Stock | B34: 300.855 | C34: 402.142 | D34: 843.936 | E34: 15.515 | F34: 23.202 | G34: 28.799 | H34: 30.613
A35: Repurchase of Common & Preferred Stk. | B35: -0.03 | C35: -0.061 | D35: -0.005 | E35: 0 | F35: 0 | G35: 0 | H35: 0
A36: Sale of Common & Preferred Stock | B36: 300.885 | C36: 402.203 | D36: 843.941 | E36: 15.515 | F36: 23.202 | G36: 28.799 | H36: 30.613
A37: Proceeds from Sale of Stock | B37: 299.888 | C37: 399.826 | D37: 842.577 | E37: -2.532 | F37: 0 | G37: 28.799 | H37: 28.799
A38: Proceeds from Stock Options | B38: 0.997 | C38: 2.377 | D38: 1.364 | E38: 18.047 | F38: 23.202 | G38: 0 | H38: 1.814
A39: Issuance/Reduction of Debt, Net | B39: 0 | C39: -0.168 | D39: -0.545 | E39: -1.303 | F39: -2.205 | G39: -1.691 | H39: -1.441
A40: Change in Long-Term Debt | B40: 0 | C40: -0.168 | D40: -0.545 | E40: -1.303 | F40: -2.205 | G40: -1.691 | H40: -1.441
A41: Reduction in Long-Term Debt | B41: 0 | C41: -0.168 | D41: -0.545 | E41: -1.303 | F41: -2.205 | G41: -1.691 | H41: -1.441
A42: Other Funds | B42: -5.002 | C42: 0 | D42: -141.747 | E42: 0 | F42: 0 | G42: -0.007 | H42: -0.007
A43: Other Uses | B43: -5.002 | C43: 0 | D43: -141.747 | E43: 0 | F43: 0 | G43: -0.007 | H43: -0.007
A44: Net Financing Cash Flow | B44: 295.853 | C44: 401.974 | D44: 701.644 | E44: 14.212 | F44: 20.997 | G44: 27.101 | H44: 29.165
A45: All Activities
A46: Exchange Rate Effect | B46: 0 | C46: 0 | D46: -0.127 | E46: 0.113 | F46: 0.477 | G46: -1.083 | H46: 0.824
A47: Net Change in Cash | B47: 73.338 | C47: 198.003 | D47: 510.001 | E47: -720.544 | F47: -69.028 | G47: 91.056 | H47: 102.806
A48: Free Cash Flow | B48: -222.515 | C48: -203.871 | D48: -190.834 | E48: -136.261 | F48: -22.768 | G48: 111.482 | H48: 169.633
A49: Free Cash Flow per Share | B49: -0.4447 | C49: -0.407439 | D49: -0.377533 | E49: -0.264955 | F49: -0.042567 | G49: 0.200393 | H49: 0.296697
A50: Free Cash Flow Yield (%) | D50: -2.266105 | E50: -1.925547 | F50: -0.130934 | G50: 0.389112 | H50: 0.82393
A51: Supplemental
A52: Taxation | B52: 0.001 | C52: 0.031 | D52: 0.467 | E52: 0.607 | F52: 2.122 | G52: 3.463 | H52: 2.42432
A53: All figures in millions of U.S. Dollar except per share items.
